Workbook

Sheet расходы спутника
A2: Наименование товара | B2: Контрагент | C2: Сумма к оплате | D2: Дата оплаты

Sheet Химки
A1: Наименование товара | B1: Контрагент | C1: Сумма к оплате | D1: Дата оплаты

Sheet Общие расходы г. Казань
B1: Общая сумма | C1: кол-во мес | D1: Сумма за месяц
A2: Расходники | C2: 12 | D2: =B2/C2 -> 0 | F2: ='Исходные данные'!E5 -> 22069 | G2: Казань
F4: =D7/F2 -> 0 | G4: р/аб
D7: =SUM(D2:D6) -> 0

Sheet Общие расходы г. Тюмень
B1: Общая сумма | C1: кол-во мес | D1: Сумма за месяц
A2: ФОТ | B2: =11300+8000 -> 19300 | C2: 12 | D2: =B2/C2 -> 1608.3333 | F2: ='Исходные данные'!E2 -> 27060 | G2: Тюмень
A3: интернет | B3: 181 | C3: 12 | D3: =B3/C3 -> 15.083333
A4: расходники | B4: =1640+8302+2570+4394+4000 -> 20906 | C4: 12 | D4: =B4/C4 -> 1742.1667 | F4: =D28/F2 -> 0.27439332 | G4: р/аб
A5: подарки | B5: 34744 | C5: 12 | D5: =B5/C5 -> 2895.3333
A6: ремонт пв | B6: 2500 | C6: 12 | D6: =B6/C6 -> 208.33333
A7: транспортные | B7: =6835+3135 -> 9970 | C7: 12 | D7: =B7/C7 -> 830.83333
A8: диагностика | B8: 1500 | C8: 12 | D8: =B8/C8 -> 125
C9: 12 | D9: =B9/C9 -> 0
C10: 12 | D10: =B10/C10 -> 0
C11: 12 | D11: =B11/C11 -> 0
C12: 12 | D12: =B12/C12 -> 0
C13: 12 | D13: =B13/C13 -> 0
C14: 12 | D14: =B14/C14 -> 0
C15: 12 | D15: =B15/C15 -> 0
C16: 12 | D16: =B16/C16 -> 0
C17: 12 | D17: =B17/C17 -> 0
C18: 12 | D18: =B18/C18 -> 0
C19: 12 | D19: =B19/C19 -> 0
C20: 12 | D20: =B20/C20 -> 0
... C27: 12 | D27: =B27/C27 -> 0
B28: =SUM(B2:B27) -> 89101 | D28: =SUM(D2:D27) -> 7425.0833
E29: кол-во аб. | F29: цена
A30: Налог УСН | B30: 376631 | C30: 12 | D30: =B30/C30 -> 31385.917 | E30: ='Исходные данные'!B2+'Исходные данные'!C2+'Исходные данные'!B40+'Исходные данные'!C40+'Исходные данные'!B41+'Исходные данные'!C41 -> 41959 | F30: =D30/E30 -> 0.74801393

Sheet Исходные данные
A1: Город | B1: кол-во аб.по домофонам | C1: кол-во по ВН | D1: кол-во под | E1: ВСЕГО
A2: Тюмень | B2: =B37 -> 23637 | C2: =C37 -> 3423 | E2: =B2+C2 -> 27060
A3: Альметьевск | B3: =B43 -> 9713 | C3: =C43 -> 6074 | E3: =B3+C3 -> 15787
A4: ЗД+о,в,н | B4: =B53 -> 11727 | C4: =C53 -> 246 | E4: =B4+C4 -> 11973
A5: Казань | B5: =B61 -> 20587 | C5: =C61 -> 1482 | E5: =B5+C5 -> 22069
A6: Инно | B6: =B66 -> 1220 | C6: =C66 -> 0 | E6: =B6+C6 -> 1220
A7: Зион | B7: =B71 -> 78 | C7: =C71 -> 532 | E7: =B7+C7 -> 610
A8: ВСЕГО | B8: =SUM(B2:B7) -> 66962 | C8: =SUM(C2:C7) -> 11757 | E8: =SUM(E2:E7) -> 78719
A9: Мастер | D9: Всего под. на обслу | E9: всего домов
A10: Олег | D10: =E37 -> 276
A11: Воронцов | D11: =F37 -> 214
A12: Полуянов | D12: =G37 -> 402
A13: Балашов | E13: =H37 -> 30
A14: ТЮМЕНЬ
B15: кол-во аб.по домофонам | C15: кол-во по ВН | D15: кол-во под. | E15: Олег | F15: Воронцов | G15: Полуянов | H15: Балашов (кол. домов)
A16: ЖСУ | B16: 4024 | C16: 86 | E16: 232 | H16: 2
A17: Надежное управление | B17: 220 | G17: 5
A18: УК Линейная | B18: 392 | G18: 8
A19: УК на Пражской | B19: 1720 | C19: 77 | G19: 100 | H19: 1
A20: Аурика | B20: 514 | G20: 14
A21: УК на Ткацком | B21: 339 | G21: 4
A22: УК Суходолье | B22: 3980 | G22: 28
A23: ТЭСК | B23: 561 | C23: 69 | E23: 2 | F23: 5 | H23: 1
A24: ЖЭУ № 9 | B24: 1298 | G24: 18
A25: Запад | B25: 6652 | C25: 754 | F25: 184 | G25: 181 | H25: 8
A26: ЮГ | B26: 43 | C26: 223 | E26: 1 | H26: 2
A27: УК Ладья | B27: 286 | F27: 8
A28: ИРИДА | B28: 997 | C28: 479 | E28: 36 | H28: 3
A29: Восток-Сити | B29: 72 | C29: 72 | G29: 2 | H29: 1
A30: На Полевой | B30: 90 | C30: 90 | F30: 1 | H30: 1
A31: Монолит | B31: 1237 | C31: 1149 | E31: 5 | G31: 9 | H31: 8
A32: УК Тобол | B32: 88 | C32: 88 | F32: 8 | H32: 1
A33: УК Усадьба | B33: 288 | F33: 8
A34: УК Высота | B34: 554 | G34: 33
A35: ТСЖ Электрон | B35: 282 | C35: 282 | H35: 1
A36: ТСН Вавилон | C36: 54 | H36: 1
A37: ИТОГО | B37: =SUM(B16:B36) -> 23637 | C37: =SUM(C16:C36) -> 3423 | D37: =SUM(D16:D29) -> 0 | E37: =SUM(E16:E36) -> 276 | F37: =SUM(F16:F36) -> 214 | G37: =SUM(G16:G36) -> 402 | H37: =SUM(H16:H36) -> 30
A38: АЛЬМЕТЬЕВСК
B39: кол-во аб.по домофонам | C39: кол-во по ВН | D39: кол-во под | E39: Кол-во камер
A40: УК Алсу | B40: 7606 | C40: 5405 | D40: =218+11 -> 229 | E40: 437
A41: УК Альметьевск | B41: 1219 | C41: 669 | D41: 50 | E41: 62
A42: Новация | B42: 888 | D42: 55
A43: ИТОГО | B43: =SUM(B40:B42) -> 9713 | C43: =SUM(C40:C42) -> 6074 | D43: =SUM(D40:D42) -> 334 | E43: =SUM(E40:E42) -> 499
A44: ЗД
B45: кол-во аб.по домофонам | C45: кол-во по ВН | D45: кол-во под
A46: Жилкомп. | B46: 10796 | C46: 0 | D46: 597
A47: Салат | B47: 114 | C47: 0 | D47: 3
A48: Радужный | B48: 246 | C48: 246 | D48: 3
A49: ТСЖ6 | B49: 288 | C49: 0 | D49: 4
A50: Тринити | D50: 15
A51: СК Иннокомфорт | D51: 4
A52: Прямые | B52: 283 | C52: 0 | D52: 9
A53: ИТОГО | B53: =SUM(B46:B52) -> 11727 | C53: =SUM(C46:C52) -> 246 | D53: =SUM(D46:D52) -> 635
A54: КАЗАНЬ
B55: кол-во аб.по домофонам | C55: кол-во по ВН | D55: кол-во под
A56: УК Московского | B56: 192 | C56: 1482 | D56: 12
A57: Фукса 12 | B57: 40 | D57: 5
A58: Радужный | B58: 1271 | D58: 75
A59: ТСЖ Современник | B59: 360 | D59: 4
A60: ЭРТХА | B60: 18724
A61: ИТОГО | B61: =SUM(B56:B60) -> 20587 | C61: =SUM(C56:C60) -> 1482 | D61: =SUM(D56:D59) -> 96
A62: ИННО
B63: кол-во аб.по домофонам/биометрия | C63: кол-во по ВН | D63: кол-во под
A64: СК Иннокомфорт | B64: 105 | C64: 0 | D64: 4
A65: Жилфонд | B65: 1115 | C65: 0 | D65: 42
A66: ИТОГО | B66: =SUM(B64:B65) -> 1220 | C66: =SUM(C64:C65) -> 0 | D66: =SUM(D64:D65) -> 46
A67: ЗИОН
B68: кол-во аб.по домофонам/биометрия | C68: кол-во по ВН | D68: кол-во под
A69: Тринити | B69: 78 | C69: 92 | D69: 15
A70: Застройщик | B70: 0 | C70: 440 | D70: 0
A71: ИТОГО | B71: =SUM(B69:B70) -> 78 | C71: =SUM(C69:C70) -> 532 | D71: =SUM(D69:D70) -> 15

Sheet Общие расходы г. Инно
B1: Общая сумма | C1: кол-во мес | D1: Сумма за месяц
A2: ГСМ | B2: 33150 | C2: 12 | D2: =B2/C2 -> 2762.5 | F2: ='Исходные данные'!E6+'Исходные данные'!E7 -> 1830 | G2: Казань
A3: Расходники | B3: =3500+442 -> 3942 | C3: 12 | D3: =B3/C3 -> 328.5
A4: интернет | C4: 12 | D4: =B4/C4 -> 0 | F4: =D20/F2 -> 1.689071 | G4: р/аб
D20: =SUM(D2:D17) -> 3091

Sheet Общие расходы г. Зеленодольск
B1: Общая сумма | C1: кол-во мес | D1: Сумма за месяц
A2: ГСМ н.вязовые | B2: 300 | C2: 12 | D2: =B2/C2 -> 25 | G2: ='Исходные данные'!E4 -> 11973 | H2: Зеленодольсе +п.г.т.
A3: Расходники | B3: =3500+11917.04+7303 -> 22720.04 | C3: 12 | D3: =B3/C3 -> 1893.3367
A4: транспортные | C4: 12 | D4: =B4/C4 -> 0 | G4: =D8/G2 -> 2.1346905 | H4: р/аб
A5: комиссия Марат Расход | B5: 163683.75 | C5: 12 | D5: =B5/C5 -> 13640.312
A6: Аренда офиса | B6: 120000 | C6: 12 | D6: =B6/C6 -> 10000
D8: =SUM(D2:D7) -> 25558.649
E11: кол-во аб. | F11: цена
A12: Налог УСН | B12: 185090 | C12: 12 | D12: =B12/C12 -> 15424.167 | E12: ='Исходные данные'!B42+'Исходные данные'!B46+'Исходные данные'!B47+'Исходные данные'!B49+'Исходные данные'!B52+'Исходные данные'!B59+'Исходные данные'!B48+'Исходные данные'!C48+'Исходные данные'!C56+'Исходные данные'!B64+'Исходные данные'!B58+'Исходные данные'!B69+'Исходные данные'!C69+'Исходные данные'!C70 -> 16689 | F12: =D12/E12 -> 0.92421156
A15: Коммисия МаратРасход | C15: 5 | D15: =B15/C15 -> 0 | E15: перенести на Альмет и Зел 75% Альм 25 % зел

Sheet Общие расходы г. Альметьевск
B1: Общая сумма | C1: кол-во мес | D1: Сумма за месяц
A2: Коммисия МаратРасход | B2: 54561 | C2: 12 | D2: =B2/C2 -> 4546.75 | F2: ='Исходные данные'!E3 -> 15787 | G2: Альметьевск
A3: Транспортные | C3: 12 | D3: =B3/C3 -> 0
A4: Расходники | B4: =16000+3660+12477+311 -> 32448 | C4: 12 | D4: =B4/C4 -> 2704 | F4: =D15/F2 -> 0.57570105 | G4: р/аб
A5: интернет | C5: 12 | D5: =B5/C5 -> 0
A6: командировка Марат, Раниф | B6: =644+10000+8410.11 -> 19054.11 | C6: 12 | D6: =B6/C6 -> 1587.8425
A7: гараж | C7: 12 | D7: =B7/C7 -> 0
A8: подарки | B8: 3000 | C8: 12 | D8: =B8/C8 -> 250
D15: =SUM(D2:D14) -> 9088.5925
A18: Коммисия МаратРасход | C18: 5 | D18: =B18/C18 -> 0 | E18: перенести на Альмет и Зел 75% Альм 25 % зел

Sheet Общие расходы ГЭ
B1: Общая сумма | C1: кол-во мес | D1: Сумма за месяц | G1: Город | H1: Кол-во абон
A2: Аренда офиса Тюмень | B2: =226800+7550 -> 234350 | C2: 12 | D2: =B2/C2 -> 19529.167 | G2: Тюмень | H2: ='Исходные данные'!E2 -> 27060
A3: Интернет Раниф тест | B3: 4080 | C3: 12 | D3: =B3/C3 -> 340 | G3: Альметьевск | H3: ='Исходные данные'!E3 -> 15787
A4: Интернет офис | B4: =6595.36+624 -> 7219.36 | C4: 12 | D4: =B4/C4 -> 601.61333 | G4: ЗД | H4: ='Исходные данные'!E4 -> 11973
A5: 8800 | B5: =171000+3000 -> 174000 | C5: 12 | D5: =B5/C5 -> 14500 | G5: Казань | H5: ='Исходные данные'!E5 -> 22069
A6: ФОТ Рафаэль | B6: 126980 | C6: 12 | D6: =B6/C6 -> 10581.667 | G6: Инно | H6: ='Исходные данные'!E6 -> 1220
A7: Процент, штраф, | B7: 602021.99 | C7: 12 | D7: =B7/C7 -> 50168.499 | G7: Зион | H7: ='Исходные данные'!E7 -> 610
A8: хостинг | B8: =4248+1400 -> 5648 | C8: 12 | D8: =B8/C8 -> 470.66667
A9: прочие (канц.товары и т.п.) | B9: =3660+3345 -> 7005 | C9: 12 | D9: =B9/C9 -> 583.75
A10: подключение интернта в офисе Тюмень | B10: 9000 | C10: 12 | D10: =B10/C10 -> 750
A11: сервер, бот | B11: 6000 | C11: 12 | D11: =B11/C11 -> 500 | G11: ВСЕГО | H11: =SUM(H2:H10) -> 78719
A12: комиссия банка | B12: =347948.83+3814+48280 -> 400042.83 | C12: 12 | D12: =B12/C12 -> 33336.903
A13: ФОТ колл-центр вторичка | B13: =168112.89+389926+394726+10341.34 -> 963106.23 | C13: 12 | D13: =B13/C13 -> 80258.852
A14: ФОТ БГ и СБ вторичка | B14: =1115475.25+540052.54+7995.3+3000+3899-30000 -> 1640422.1 | C14: 12 | D14: =B14/C14 -> 136701.84
A15: ФОТ БГ и СБ первичка | B15: =1277731.33+1885051 -> 3162782.3 | C15: 12 | D15: =B15/C15 -> 263565.19
A16: налог Малащенко ТН | B16: 36409.13 | C16: 12 | D16: =B16/C16 -> 3034.0942 | G16: =D23/H11 -> 9.1731977 | H16: р/аб
A17: Налоги с ФОТ БГ и СБ | B17: =535961.42+657136.97 -> 1193098.4 | C17: 12 | D17: =B17/C17 -> 99424.866
A18: Прочие, почтовые | B18: 7843 | C18: 12 | D18: =B18/C18 -> 653.58333
A19: ЭДО, почта | B19: 39866 | C19: 12 | D19: =B19/C19 -> 3322.1667
A20: Транспортные | B20: 18885 | C20: 12 | D20: =B20/C20 -> 1573.75
A21: Аренда склада в Казани | B21: 22000 | C21: 12 | D21: =B21/C21 -> 1833.3333
A22: подарки (представительские расходы) | B22: 4500 | C22: 12 | D22: =B22/C22 -> 375
B23: =SUM(B2:B22) -> 8665259.3 | D23: =SUM(D2:D22) -> 722104.95

Sheet Доход-Расход
I1: ТЮМЕНЬ | Y1: АЛЬМЕТЬЕВСК | AC1: ЗЕЛЕНОДОЛЬСК | AI1: КАЗАНЬ | AO1: ИННОПОЛИС
A2: УК | C2: Монолит | D2: Усадьба | E2: Тобол | F2: Высота | G2: Вавилон | H2: Электрон | I2: Запад | J2: Ирида | K2: ЖСУ | L2: Суходолье | M2: Линейная | N2: Аурика | O2: Надежное | P2: ЖЭУ 9 | Q2: УК на Ткацком | R2: На Пражской | S2: ТЭСК | T2: Восток-сити | U2: Ладья | V2: ЮГ | W2: УК на Полевой | Y2: УК Алсу | Z2: УК Альметьевск | AA2: Новация | AC2: Жилкомплекс | AD2: Радужный | AE2: Салават | AF2: ТСЖ №6 | AG2: Прямые | AI2: Радужный (Казань) | AJ2: ЖК Моск.р-на | AK2: Фукса 12 | AL2: Современник | AM2: ЭРТХА | AO2: Тринити | AP2: Жилищный фонд | AQ2: ЗИОН | AR2: Иннокомфорт
A3: Доход (выставленные счета) | C3: =231837.91/12 -> 19319.826 | D3: =107543.76/12 -> 8961.98 | E3: =75349.2/12 -> 6279.1 | F3: =115456.3/12 -> 9621.3583 | G3: 0 | H3: 37712 | I3: =3132747.07/12 -> 261062.26 | J3: =672555.97/12 -> 56046.331 | K3: =1727530.9/12 -> 143960.91 | L3: =1443030/12 -> 120252.5 | M3: =141120/12 -> 11760 | N3: =247620/12 -> 20635 | O3: =77551.35/12 -> 6462.6125 | P3: =541317.35/12 -> 45109.779 | Q3: =145189.45/12 -> 12099.121 | R3: =1025987.37/12 -> 85498.947 | S3: =254419.6/12 -> 21201.633 | T3: =108500/12 -> 9041.6667 | U3: =100872.9/12 -> 8406.075 | V3: =122341.43/12 -> 10195.119 | W3: =108000/12 -> 9000 | Y3: =7441060.31/12 -> 620088.36 | Z3: =1164623.41/12 -> 97051.951 | AA3: =222272.01/12 -> 18522.667 | AC3: =3891384/12 -> 324282 | AD3: =199127/12 -> 16593.917 | AE3: =34800/12 -> 2900 | AF3: 5580 | AG3: =88105/12 -> 7342.0833 | AI3: =311698/12 -> 25974.833 | AJ3: =1299497.16/12 -> 108291.43 | AK3: =22140/12 -> 1845 | AL3: =130783/12 -> 10898.583 | AM3: =3818677/12 -> 318223.08 | AO3: =270120/12 -> 22510 | AP3: =460246.81/12 -> 38353.901 | AQ3: =496800/12 -> 41400 | AR3: =50250/12 -> 4187.5
A4: Доход (фактически полученные ДС) | C4: =231837.91/12 -> 19319.826 | D4: =81201.27/12 -> 6766.7725 | E4: =104461.56/12 -> 8705.13 | F4: =89061.62/12 -> 7421.8017 | G4: 0 | H4: 0 | I4: =2242086.98/12 -> 186840.58 | J4: =552780.75/12 -> 46065.062 | K4: =1731914.37/12 -> 144326.2 | L4: =1385460/12 -> 115455 | M4: =141120/12 -> 11760 | N4: =227060/12 -> 18921.667 | O4: =77551.35/12 -> 6462.6125 | P4: =541507.34/12 -> 45125.612 | Q4: =145189.45/12 -> 12099.121 | R4: =598896.67/12 -> 49908.056 | S4: =254419.6/12 -> 21201.633 | T4: =108500/12 -> 9041.6667 | U4: =105052.8/12 -> 8754.4 | V4: =119038.28/12 -> 9919.8567 | W4: =108000/12 -> 9000 | Y4: =7431179.15/12 -> 619264.93 | Z4: =1164623.41/12 -> 97051.951 | AA4: =222991.21/12 -> 18582.601 | AC4: =3804813.12/12 -> 317067.76 | AD4: =199127/12 -> 16593.917 | AE4: =44800/12 -> 3733.3333 | AF4: 5580 | AG4: =93781/12 -> 7815.0833 | AI4: =312927/12 -> 26077.25 | AJ4: =1244692.4/12 -> 103724.37 | AK4: =22140/12 -> 1845 | AL4: =130983/12 -> 10915.25 | AM4: =3842756/12 -> 320229.67 | AO4: =266200/12 -> 22183.333 | AP4: =459166.91/12 -> 38263.909 | AQ4: =496800/12 -> 41400 | AR4: =59750/12 -> 4979.1667 | AT4: =SUM(C4:AR4) -> 2392402.5
B5: разница | C5: =C3-C4 -> 0 | D5: =D3-D4 -> 2195.2075 | E5: =E3-E4 -> -2426.03 | F5: =F3-F4 -> 2199.5567 | G5: =G3-G4 -> 0 | H5: =H3-H4 -> 37712 | I5: =I3-I4 -> 74221.674 | J5: =J3-J4 -> 9981.2683 | ... W5: =W3-W4 -> 0 | Y5: =Y3-Y4 -> 823.43 | Z5: =Z3-Z4 -> 0 | AA5: =AA3-AA4 -> -59.933333 | AC5: =AC3-AC4 -> 7214.24 | AD5: =AD3-AD4 -> 0 | AE5: =AE3-AE4 -> -833.33333 | AF5: =AF3-AF4 -> 0 | AG5: =AG3-AG4 -> -473 | AI5: =AI3-AI4 -> -102.41667 | AJ5: =AJ3-AJ4 -> 4567.0633 | AK5: =AK3-AK4 -> 0 | AL5: =AL3-AL4 -> -16.666667 | AM5: =AM3-AM4 -> -2006.5833 | AO5: =AO3-AO4 -> 326.66667 | AP5: =AP3-AP4 -> 89.991667 | AQ5: =AQ3-AQ4 -> 0 | AR5: =AR3-AR4 -> -791.66667
A6: Доход от продаж | C6: =56100/12 -> 4675 | D6: =1000/12 -> 83.333333 | E6: =1000/12 -> 83.333333 | F6: =18600/12 -> 1550 | H6: =64950/12 -> 5412.5 | I6: =90400/12 -> 7533.3333 | J6: =27300/12 -> 2275 | K6: =89100/12 -> 7425 | L6: =18700/12 -> 1558.3333 | M6: =2000/12 -> 166.66667 | N6: =24400/12 -> 2033.3333 | O6: =1000/12 -> 83.333333 | P6: =7150/12 -> 595.83333 | Q6: =20600/12 -> 1716.6667 | R6: =5600/12 -> 466.66667 | S6: =21200/12 -> 1766.6667 | T6: =1200/12 -> 100 | W6: =1000/12 -> 83.333333 | Y6: =102200/12 -> 8516.6667 | Z6: =5400/12 -> 450 | AC6: =(306650+19200)/12 -> 27154.167 | AF6: =400/12 -> 33.333333 | AI6: =9800/12 -> 816.66667 | AL6: =2800/12 -> 233.33333
A7: Расход | B7: ФОТ | C7: =Монолит!I3+Монолит!I4+Монолит!I5 -> 8594.7594 | D7: =Усадьба!I3 -> 1496.6355 | E7: =Тобол!I3+Тобол!I4 -> 2346.2688 | F7: =Высота!I3+Высота!I4 -> 5986.8147 | G7: =Вавилон!I3 -> 0 | H7: =Электрон!I3+Электрон!I4 -> 849.63333 | I7: =Запад!I3+Запад!I4+Запад!I5 -> 67133.294 | J7: =Ирида!I3+Ирида!I4+Ирида!I5 -> 6927.2696 | K7: =ЖСУ!I3+ЖСУ!I4 -> 29915.426 | L7: =Суходолье!I3+Суходолье!I4 -> 3700.9337 | M7: ='УК линейная'!I3 -> 1057.4096 | N7: ='Аурика '!I3+'Аурика '!I4 -> 1850.4668 | O7: ='Надежное управление'!I3+'Надежное управление'!I5 -> 660.88101 | P7: ='ЖЭУ 9'!I3+'ЖЭУ 9'!I4 -> 2379.1716 | Q7: ='УК на Ткацком'!I3 -> 528.70481 | R7: ='УК на пражской'!I3+'УК на пражской'!I4 -> 14067.254 | S7: =ТЭСК!I3+ТЭСК!I4+ТЭСК!I5 -> 2028.2733 | T7: ='Восток сити'!I3+'Восток сити'!I4 -> 1113.9857 | U7: =Ладья!I3 -> 1496.6355 | V7: =Юг!I4+Юг!I3 -> 1820.888 | W7: ='УК на Полевой'!I3+'УК на Полевой'!I4 -> 1036.7128 | Y7: =Алсу!I3+Алсу!I4 -> 77259.243 | Z7: ='УК Альметьевск'!I2+'УК Альметьевск'!I3+'УК Альметьевск'!I4 -> 10677.985 | AA7: =Новация!I2 -> 3818.9459 | AC7: =Жилкомплекс!I2 -> 71314.941 | AD7: =Радужный_З!I2 -> 355.13819 | AE7: ='Салават Купере'!I2 -> 355.13819 | AF7: ='ТСЖ №6'!I2 -> 473.51759 | AG7: =Прямые!I2 -> 1065.4146 | AI7: ='Радужный (Казань)'!I2 -> 8497.6562 | AJ7: ='ЖК Моск рай-на'!H2+'ЖК Моск рай-на'!H3 -> 9541.6667 | AK7: ='Фукса 12'!I2 -> 566.51042 | AL7: ='ТСЖ Соврменник'!I3 -> 453.20833 | AM7: =ЭРТХ_К!G2 -> 184780.92 | AO7: =Тринити!I2+Тринити!I3 -> 129.92126 | AP7: ='Жилищный фонд'!I2 -> 2150 | AQ7: =ЗИОН!I2+ЗИОН!I4 -> 1216.3462 | AR7: ='СК Иннокомфорт'!I2 -> 473.51759
B8: Оборудование (Сервис) | C8: =Монолит!I8+Монолит!I12+Монолит!I11 -> 2333.09 | D8: =Усадьба!I6 -> 127.91667 | E8: =Тобол!I7 -> 182.5 | F8: =Высота!I6+Высота!I10 -> 241.33333 | G8: =Вавилон!I6 -> 0 | H8: =Электрон!I7 -> 46.166667 | I8: =Запад!I9+Запад!I12 -> 17670.667 | J8: =Ирида!I6+Ирида!I9+Ирида!I10 -> 2912.5 | K8: =ЖСУ!I7+ЖСУ!I10+ЖСУ!I12 -> 10697.167 | L8: =Суходолье!I6+Суходолье!I9+Суходолье!I10 -> 5431.3333 | M8: ='УК линейная'!I4+'УК линейная'!I7 -> 213.75 | N8: ='Аурика '!I7+'Аурика '!I10+'Аурика '!I12 -> 6767 | O8: ='Надежное управление'!I6+'Надежное управление'!I9 -> 73.75 | P8: ='ЖЭУ 9'!I5+'ЖЭУ 9'!I8 -> 1278.6667 | R8: ='УК на пражской'!I6+'УК на пражской'!I11 -> 9453.1667 | S8: =ТЭСК!I6+ТЭСК!I9 -> 1162 | T8: ='Восток сити'!I7+'Восток сити'!I12 -> 880.16667 | U8: =Ладья!I5 -> 1537.9167 | V8: =Юг!I6+Юг!I9 -> 393.83333 | W8: ='УК на Полевой'!I7+'УК на Полевой'!I10+'УК на Полевой'!I12 -> 44.583333 | Y8: =Алсу!I6+Алсу!I9 -> 27971.75 | Z8: ='УК Альметьевск'!I10 -> 4724.6667 | AA8: =Новация!I3 -> 269.70833 | AC8: =Жилкомплекс!I5 -> 22333.333 | AD8: =Радужный_З!I4 -> 0 | AF8: ='ТСЖ №6'!I5 -> 2.1666667 | AI8: ='Радужный (Казань)'!I6 -> 0 | AJ8: ='ЖК Моск рай-на'!H6+'ЖК Моск рай-на'!H9+'ЖК Моск рай-на'!H8 -> 1733.6667 | AK8: ='Фукса 12'!I3 -> 0 | AL8: ='ТСЖ Соврменник'!I6 -> 89.583333 | AM8: =ЭРТХ_К!G3 -> 1266.6667 | AO8: =Тринити!I5 -> 5685.6667 | AP8: ='Жилищный фонд'!I3 -> 0 | AQ8: =ЗИОН!I5 -> 3939.6667 | AR8: ='СК Иннокомфорт'!I4 -> 2222.1667
B9: Оборудование (Модернизация) | C9: =Монолит!I10 -> 0 | F9: =Высота!I8 -> 1107.25 | G9: =Вавилон!I8 -> 0 | H9: =Электрон!I9 -> 0 | I9: =Запад!I11 -> 0 | J9: =Ирида!I8 -> 0 | K9: =ЖСУ!I9 -> 0 | L9: =Суходолье!I8 -> 0 | M9: ='УК линейная'!I5 -> 0 | N9: ='Аурика '!I9 -> 0 | P9: ='ЖЭУ 9'!I7 -> 0 | R9: ='УК на пражской'!I8 -> 2291.0833 | S9: =ТЭСК!I8 -> 0 | T9: ='Восток сити'!I9 -> 0 | V9: =Юг!I8 -> 0 | W9: ='УК на Полевой'!I9 -> 0 | Y9: =Алсу!I8 -> 6724.4167 | Z9: ='УК Альметьевск'!I12 -> 0 | AC9: =Жилкомплекс!I7 -> 61500 | AG9: =Прямые!I4 -> 0 | AL9: ='ТСЖ Соврменник'!I8 -> 0
B10: Оборудование (Кап.вложения) | C10: =Монолит!I9 -> 40053 | F10: =Высота!I7 -> 0 | G10: =Вавилон!I7 -> 0 | H10: =Электрон!I8 -> 14819.417 | I10: =Запад!I10 -> 11103.75 | J10: =Ирида!I7 -> 0 | K10: =ЖСУ!I8 -> 0 | M10: ='УК линейная'!I5 -> 0 | N10: ='Аурика '!I8 -> 0 | P10: ='ЖЭУ 9'!I6 -> 3150.5833 | R10: ='УК на пражской'!I7 -> 0 | S10: =ТЭСК!I7 -> 3764.8333 | T10: ='Восток сити'!I8 -> 265 | V10: =Юг!I7 -> 0 | W10: ='УК на Полевой'!I8 -> 0 | Y10: =Алсу!I7 -> 8508.3333 | Z10: ='УК Альметьевск'!I11 -> 8433.9167 | AC10: =Жилкомплекс!I6 -> 0 | AJ10: ='ЖК Моск рай-на'!H5 -> 11626.833 | AL10: ='ТСЖ Соврменник'!I7 -> 0
B11: Интернет | C11: =Монолит!I7 -> 2468.9167 | F11: =Высота!I5 -> 554.16667 | G11: =Вавилон!I5 -> 270 | H11: =Электрон!I6 -> 95.833333 | I11: =Запад!I7+Запад!I8 -> 28494.517 | J11: =Ирида!I11 -> 2280.4167 | K11: =ЖСУ!I5+ЖСУ!I6 -> 14419.438 | L11: =Суходолье!I5 -> 7200 | N11: ='Аурика '!I5 -> 1316 | P11: ='ЖЭУ 9'!I9 -> 861.58333 | Q11: ='УК на Ткацком'!I7 -> 3333.3333 | R11: ='УК на пражской'!I5 -> 4765.9167 | S11: =ТЭСК!I11 -> 432.41083 | T11: ='Восток сити'!I5 -> 681.66667 | U11: =Ладья!I4 -> 758.33333 | V11: =Юг!I5 -> 706.25 | W11: ='УК на Полевой'!I6 -> 625.96833 | Y11: =Алсу!I5 -> 21308.417 | Z11: ='УК Альметьевск'!I5 -> 5238.8333 | AC11: =Жилкомплекс!I3 -> 14411.917 | AD11: =Радужный_З!I3 -> 1783.3333 | AF11: ='ТСЖ №6'!I3 -> 502 | AI11: ='Радужный (Казань)'!I3 -> 511.66667 | AJ11: ='ЖК Моск рай-на'!H4 -> 7855.0833 | AL11: ='ТСЖ Соврменник'!I5+'ТСЖ Соврменник'!I4 -> 0 | AO11: =Тринити!I4 -> 6914.25 | AQ11: =ЗИОН!I3 -> 6283.75 | AR11: ='СК Иннокомфорт'!I3 -> 1243.75
B12: Общие расходы ГЭ | C12: =Монолит!I14 -> 21887.25 | D12: =Усадьба!I12 -> 2641.8809 | E12: =Тобол!I13 -> 1614.4828 | F12: =Высота!I12 -> 5081.9515 | G12: =Вавилон!I12 -> 495.35267 | H12: =Электрон!I13 -> 5173.6835 | I12: =Запад!I17 -> 67936.702 | J12: =Ирида!I13 -> 13539.64 | K12: =ЖСУ!I13 -> 37701.842 | L12: =Суходолье!I12 -> 36509.327 | M12: ='УК линейная'!I8 -> 3595.8935 | N12: ='Аурика '!I13 -> 4715.0236 | O12: ='Надежное управление'!I10 -> 2018.1035 | P12: ='ЖЭУ 9'!I11 -> 11906.811 | Q12: ='УК на Ткацком'!I8 -> 3109.714 | R12: ='УК на пражской'!I12 -> 15777.9 | S12: =ТЭСК!I12 -> 3999.5142 | T12: ='Восток сити'!I13 -> 1320.9405 | U12: =Ладья!I9 -> 2623.5345 | V12: =Юг!I10 -> 2440.0706 | W12: ='УК на Полевой'!I13 -> 1651.1756 | Y12: =Алсу!I15 -> 119352.47 | Z12: ='УК Альметьевск'!I16 -> 17318.997 | AA12: =Новация!I5 -> 8145.7995 | AC12: =Жилкомплекс!I12 -> 99033.842 | AD12: =Радужный_З!I6 -> 4513.2132 | AE12: ='Салават Купере'!I3 -> 1045.7445 | AF12: ='ТСЖ №6'!I6 -> 2641.8809 | AG12: =Прямые!I5 -> 2596.0149 | AI12: ='Радужный (Казань)'!I8 -> 11659.134 | AJ12: ='ЖК Моск рай-на'!H12 -> 15355.933 | AK12: ='Фукса 12'!I5 -> 366.92791 | AL12: ='ТСЖ Соврменник'!I12 -> 3302.3512 | AM12: =ЭРТХ_К!G4 -> 0 | AO12: =Тринити!I6 -> 1559.4436 | AP12: ='Жилищный фонд'!I5 -> 10228.115 | AQ12: =ЗИОН!I7 -> 4036.207 | AR12: ='СК Иннокомфорт'!I5 -> 963.18575
B13: Общие расходы города | C13: =Монолит!I15 -> 654.70247 | D13: =Усадьба!I13 -> 79.025277 | E13: =Тобол!I14 -> 48.293225 | F13: =Высота!I13 -> 152.0139 | G13: =Вавилон!I13 -> 14.817239 | H13: =Электрон!I14 -> 154.75783 | I13: =Запад!I18 -> 2032.157 | J13: =Ирида!I14 -> 405.00455 | K13: =ЖСУ!I14 -> 1127.7566 | L13: =Суходолье!I13 -> 1092.0854 | M13: ='УК линейная'!I9 -> 107.56218 | N13: ='Аурика '!I14 -> 141.03817 | O13: ='Надежное управление'!I11 -> 60.366531 | P13: ='ЖЭУ 9'!I12 -> 356.16253 | Q13: ='УК на Ткацком'!I9 -> 93.019337 | R13: ='УК на пражской'!I13 -> 471.95652 | S13: =ТЭСК!I13 -> 119.63549 | T13: ='Восток сити'!I14 -> 39.512639 | U13: =Ладья!I10 -> 78.476491 | V13: =Юг!I11 -> 72.988624 | W13: ='УК на Полевой'!I14 -> 49.390798 | Y13: =Алсу!I14 -> 7490.4464 | Z13: ='УК Альметьевск'!I15 -> 1086.9236 | AA13: =Новация!I4 -> 511.22253 | AC13: =Жилкомплекс!I13 -> 23046.118 | AD13: =Радужный_З!I7 -> 1050.2677 | AE13: ='Салават Купере'!I4 -> 243.35472 | AF13: ='ТСЖ №6'!I7 -> 614.79086 | AG13: =Прямые!I6 -> 604.11741 | AI13: ='Радужный (Казань)'!I7 -> 0 | AJ13: ='ЖК Моск рай-на'!H11 -> 0 | AK13: ='Фукса 12'!I4 -> 0 | AL13: ='ТСЖ Соврменник'!I13 -> 0 | AO13: =Тринити!I7 -> 287.14208 | AP13: ='Жилищный фонд'!I6 -> 1883.3142 | AQ13: =ЗИОН!I8 -> 743.19126 | AR13: ='СК Иннокомфорт'!I6 -> 177.35246
B14: Услуги УК | C14: =Монолит!I6 -> 841.66667 | E14: =Тобол!I15 -> 131.65045 | G14: =Вавилон!I4 -> 0 | H14: =Электрон!I5 -> 0 | I14: =Запад!I6+Запад!I15 -> 71946.583 | Y14: =Алсу!I13+Алсу!I11 -> 62563.25 | Z14: ='УК Альметьевск'!I14+'УК Альметьевск'!I9 -> 15997.5 | AC14: =Жилкомплекс!I8+Жилкомплекс!I10 -> 46583.333 | AD14: =Радужный_З!AA8 -> 0 | AG14: =Прямые!AA7 -> 0 | AJ14: ='ЖК Моск рай-на'!H7 -> 317.20333
B15: Кап.вложения | C15: =Монолит!I13 -> 49421.667 | F15: =Высота!I11 -> 0 | G15: =Вавилон!I11 -> 2375 | H15: =Электрон!I12 -> 12360.333 | I15: =Запад!I16 -> 17035.417 | J15: =Ирида!I12 -> 0 | K15: =ЖСУ!I11 -> 2833.3333 | L15: =Суходолье!I11 -> 0 | M15: ='УК линейная'!I6 -> 0 | N15: ='Аурика '!I11 -> 0 | P15: ='ЖЭУ 9'!I10 -> 0 | R15: ='УК на пражской'!I10 -> 0 | S15: =ТЭСК!I10 -> 2262.4167 | T15: ='Восток сити'!I11 -> 291.66667 | V15: =Юг!I8 -> 0 | W15: ='УК на Полевой'!I11 -> 0 | Y15: =Алсу!I12 -> 23448.083 | Z15: ='УК Альметьевск'!I13 -> 0 | AC15: =Жилкомплекс!I11 -> 25416.667 | AG15: =Прямые!I3 -> 0 | AI15: ='Радужный (Казань)'!I5 -> 0 | AJ15: ='ЖК Моск рай-на'!H10 -> 5400 | AL15: ='ТСЖ Соврменник'!I10 -> 0
B16: УСН | C16: =Монолит!I16 -> 1784.7612 | D16: =Усадьба!I14 -> 215.42801 | F16: =Высота!I14 -> 414.39972 | G16: =Вавилон!I14 -> 40.392752 | H16: =Электрон!I15 -> 421.87986 | I16: =Запад!I19 -> 5539.7912 | J16: =Ирида!I15 -> 1104.0686 | K16: =ЖСУ!I15 -> 3074.3373 | L16: =Суходолье!I14 -> 2977.0955 | M16: ='УК линейная'!I10 -> 293.22146 | N16: ='Аурика '!I15 -> 384.47916 | O16: ='Надежное управление'!I12 -> 164.56307 | P16: ='ЖЭУ 9'!I13 -> 970.92209 | Q16: ='УК на Ткацком'!I10 -> 253.57672 | R16: ='УК на пражской'!I14 -> 1286.584 | S16: =ТЭСК!I14 -> 326.13408 | T16: ='Восток сити'!I15 -> 107.71401 | U16: =Ладья!I11 -> 213.93199 | V16: =Юг!I12 -> 198.97171 | W16: ='УК на Полевой'!I15 -> 134.64251 | Y16: =Алсу!I16 -> 9732.4093 | Z16: ='УК Альметьевск'!I17 -> 1412.2503 | AA16: =Новация!I6 -> 820.69986 | AC16: =Жилкомплекс!I14 -> 9977.788 | AD16: =Радужный_З!I8 -> 454.71209 | AE16: ='Салават Купере'!I5 -> 105.36012 | AF16: ='ТСЖ №6'!I8 -> 266.17293 | AG16: =Прямые!I7 -> 261.55187 | AI16: ='Радужный (Казань)'!I9 -> 1174.6729 | AJ16: ='ЖК Моск рай-на'!H13 -> 1547.1301 | AL16: ='ТСЖ Соврменник'!I14 -> 332.71616 | AO16: =Тринити!I8 -> 157.11596 | AP16: ='Жилищный фонд'!I7 -> 0 | AQ16: =ЗИОН!I9 -> 406.65308 | AR16: ='СК Иннокомфорт'!I7 -> 97.042213
A17: Итого расходов | C17: =SUM(C7:C16) -> 128039.81 | D17: =SUM(D7:D16) -> 4560.8864 | E17: =SUM(E7:E16) -> 4323.1953 | F17: =SUM(F7:F16) -> 13537.93 | G17: =SUM(G7:G16) -> 3195.5627 | H17: =SUM(H7:H16) -> 33921.705 | I17: =SUM(I7:I16) -> 288892.88 | J17: =SUM(J7:J16) -> 27168.899 | ... W17: =SUM(W7:W16) -> 3542.4733 | Y17: =SUM(Y7:Y16) -> 364358.82 | Z17: =SUM(Z7:Z16) -> 64891.073 | AA17: =SUM(AA7:AA16) -> 13566.376 | AC17: =SUM(AC7:AC16) -> 373617.94 | AD17: =SUM(AD7:AD16) -> 8156.6646 | AE17: =SUM(AE7:AE16) -> 1749.5976 | AF17: =SUM(AF7:AF16) -> 4500.529 | AG17: =SUM(AG7:AG16) -> 4527.0988 | AI17: =SUM(AI7:AI16) -> 21843.13 | AJ17: =SUM(AJ7:AJ16) -> 53377.516 | AK17: =SUM(AK7:AK16) -> 933.43832 | AL17: =SUM(AL7:AL16) -> 4177.859 | AM17: =SUM(AM7:AM16) -> 186047.58 | AO17: =SUM(AO7:AO16) -> 14733.54 | AP17: =SUM(AP7:AP16) -> 14261.43 | AQ17: =SUM(AQ7:AQ16) -> 16625.814 | AR17: =SUM(AR7:AR16) -> 5177.0147 | AT17: =SUM(C17:AR17) -> 1947302.2 | AU17: =24551172/12 -> 2045931 | AV17: =AU17-AT17 -> 98628.839
B19: ИТОГ 2025 | C19: =C4+C6-C17 -> -104044.99 | D19: =D4+D6-D17 -> 2289.2194 | E19: =E4+E6-E17 -> 4465.268 | F19: =F4+F6-F17 -> -4566.1281 | G19: =G4+G6-G17 -> -3195.5627 | H19: =H4+H6-H17 -> -28509.205 | I19: =I4+I6-I17 -> -94518.962 | J19: =J4+J6-J17 -> 21171.163 | ... W19: =W4+W6-W17 -> 5540.86 | Y19: =Y4+Y6-Y17 -> 263422.77 | Z19: =Z4+Z6-Z17 -> 32610.878 | AA19: =AA4+AA6-AA17 -> 5016.2247 | AC19: =AC4+AC6-AC17 -> -29396.012 | AD19: =AD4+AD6-AD17 -> 8437.2521 | AE19: =AE4+AE6-AE17 -> 1983.7358 | AF19: =AF4+AF6-AF17 -> 1112.8044 | AG19: =AG4+AG6-AG17 -> 3287.9846 | AI19: =AI4+AI6-AI17 -> 5050.7866 | AJ19: =AJ4+AJ6-AJ17 -> 50346.85 | AK19: =AK4+AK6-AK17 -> 911.56168 | AL19: =AL4+AL6-AL17 -> 6970.7244 | AM19: =AM4+AM6-AM17 -> 134182.08 | AO19: =AO4+AO6-AO17 -> 7449.7938 | AP19: =AP4+AP6-AP17 -> 24002.48 | AQ19: =AQ4+AQ6-AQ17 -> 24774.186 | AR19: =AR4+AR6-AR17 -> -197.84801 | AT19: =SUM(C19:AR19) -> 519912.85

Sheet по годам
A1: Название УК | B1: 2022 год | C1: 2023 год | D1: 2024 год | E1: 2025 год
A2: ООО УК Запад | E2: -94306
A3: ООО УК Ирида | E3: 21214
A4: ООО ЖСУ | E4: 52100
A5: ООО УК Суходолье | E5: 60217
A6: ООО УК Линейная | E6: 6670
A7: ООО Надежное управление | E7: 3575
A8: ООО УК Аурика | E8: 5796
A9: ООО ЖЭУ № 9 | E9: 24855
A10: ООО УК На Ткацком | E10: 6507
A11: ООО УК На Пражской | E11: 2310
A12: Монолит | E12: -103976
A13: Усадьба | E13: 2298
... A39: ООО Иннокомфорт | E39: -195

Sheet Монолит
A2: МОНОЛИТ | B2: Всего на обсл. под. | C2: Кол-во под. по ук | D2: Кол-во абонентов | E2: Общая сумма | F2: кол-во мес | G2: р/аб | H2: Сумма за месяц | I2: Сумма расхода на УК
A3: ФОТ Полуянов | B3: ='Исходные данные'!D12 -> 402 | C3: ='Исходные данные'!G31 -> 9 | E3: 637618 | F3: 12 | H3: =E3/F3 -> 53134.833 | I3: =H3/B3*C3 -> 1189.5858
A4: ФОТ Артем | B4: ='Исходные данные'!D10 -> 276 | C4: ='Исходные данные'!E31 -> 5 | E4: 402810 | F4: 12 | H4: =E4/F4 -> 33567.5 | I4: =H4/B4*C4 -> 608.10688
A5: ФОТ Балашев | B5: ='Исходные данные'!E13 -> 30 | C5: ='Исходные данные'!H31 -> 8 | E5: 305868 | F5: 12 | H5: =E5/F5 -> 25489 | I5: =H5/B5*C5 -> 6797.0667
A6: Услуги УК | E6: 10100 | F6: 12 | H6: =E6/F6 -> 841.66667 | I6: =H6 -> 841.66667
A7: Интернет физ.лица | E7: =1500+28127 -> 29627 | F7: 12 | H7: =E7/F7 -> 2468.9167 | I7: =H7 -> 2468.9167
A8: Оборудование (Сервис) | E8: 21923 | F8: 12 | H8: =E8/F8 -> 1826.9167 | I8: =H8 -> 1826.9167
A9: Оборудование (Кап.вложения) | E9: 480636 | F9: 12 | H9: =E9/F9 -> 40053 | I9: =H9 -> 40053
A10: Оборудование (Модернизация) | E10: 0 | F10: 12 | H10: =E10/F10 -> 0 | I10: =H10 -> 0
A11: Расходники по УК | E11: =794+460+2805.08 -> 4059.08 | F11: 12 | H11: =E11/F11 -> 338.25667 | I11: =H11 -> 338.25667
A12: Транспортные по УК | E12: =793+1222 -> 2015 | F12: 12 | H12: =E12/F12 -> 167.91667 | I12: =H12 -> 167.91667
A13: Кап.вложения | H13: =D30 -> 49421.667 | I13: =H13 -> 49421.667
A14: Общие расходы ГЭ | D14: =B19+B20 -> 2386 | G14: ='Общие расходы ГЭ'!G16 -> 9.1731977 | I14: =D14*G14 -> 21887.25
A15: Общие расходы города | D15: =B19+B20 -> 2386 | G15: ='Общие расходы г. Тюмень'!F4 -> 0.27439332 | I15: =D15*G15 -> 654.70247
A16: УСН | D16: =B19+B20 -> 2386 | G16: ='Общие расходы г. Тюмень'!F30 -> 0.74801393 | I16: =D16*G16 -> 1784.7612
A17: ИТОГО | I17: =SUM(I3:I16) -> 128039.81
A19: Абонентов домофония | B19: ='Исходные данные'!B31 -> 1237
A20: Абонентов ВН | B20: ='Исходные данные'!C31 -> 1149
A21: Подъездов | B21: ='Исходные данные'!D25 -> 0
A23: КАП.ВЛОЖЕНИЯ
A24: Наименование | B24: Общая сумма | C24: кол-во мес | D24: Итого
A25: Монтажи фот | B25: =104500+218500+41500+24000+85500+77000 -> 551000 | C25: 12 | D25: =B25/C25 -> 45916.667
A26: подключение новых точек | B26: 31240 | C26: 12 | D26: =B26/C26 -> 2603.3333
A27: расходники | B27: 10820 | C27: 12 | D27: =B27/C27 -> 901.66667
B30: =SUM(B25:B29) -> 593060 | C30: 12 | D30: =B30/C30 -> 49421.667

Sheet Усадьба
A2: УСАДЬБА | B2: Всего на обсл. под. | C2: Кол-во под. по ук | D2: Кол-во абонентов | E2: Общая сумма | F2: кол-во мес | G2: р/аб | H2: Сумма за месяц | I2: Сумма расхода на УК
A3: ФОТ Воронцов | B3: ='Исходные данные'!D11 -> 214 | C3: ='Исходные данные'!F33 -> 8 | E3: 480420 | F3: 12 | H3: =E3/F3 -> 40035 | I3: =H3/B3*C3 -> 1496.6355
A4: Услуги УК | F4: 12 | H4: =E4/F4 -> 0 | I4: =H4 -> 0
A5: Интернет физ.лица | F5: 12 | H5: =E5/F5 -> 0 | I5: =H5 -> 0
A6: Оборудование (Сервис) | E6: 1535 | F6: 12 | H6: =E6/F6 -> 127.91667 | I6: =H6 -> 127.91667
A7: Оборудование (Кап.вложения) | E7: 0 | F7: 12 | H7: =E7/F7 -> 0 | I7: =H7 -> 0
A8: Оборудование (Модернизация) | E8: 0 | F8: 12 | H8: =E8/F8 -> 0 | I8: =H8 -> 0
A9: Расходники по УК | F9: 12 | H9: =E9/F9 -> 0 | I9: =H9 -> 0
A10: Транспортные по УК | F10: 12 | H10: =E10/F10 -> 0 | I10: =H10 -> 0
A11: Кап.вложения | H11: =D28 -> 0 | I11: =H11 -> 0
A12: Общие расходы ГЭ | D12: =B17+B18 -> 288 | G12: ='Общие расходы ГЭ'!G16 -> 9.1731977 | I12: =D12*G12 -> 2641.8809
A13: Общие расходы города | D13: =B17+B18 -> 288 | G13: ='Общие расходы г. Тюмень'!F4 -> 0.27439332 | I13: =D13*G13 -> 79.025277
A14: УСН | D14: =B17+B18 -> 288 | G14: ='Общие расходы г. Тюмень'!F30 -> 0.74801393 | I14: =D14*G14 -> 215.42801
A15: ИТОГО | I15: =SUM(I3:I14) -> 4560.8864
A17: Абонентов домофония | B17: ='Исходные данные'!B33 -> 288
A18: Абонентов ВН | B18: ='Исходные данные'!C33 -> 0
A19: Подъездов | B19: ='Исходные данные'!D25 -> 0
A21: КАП.ВЛОЖЕНИЯ
A22: Наименование | B22: Общая сумма | C22: кол-во мес | D22: Итого
A23: Монтажи фот | C23: 12 | D23: =B23/C23 -> 0
A24: подключение новой точки | C24: 12 | D24: =B24/C24 -> 0
B28: =SUM(B23:B27) -> 0 | C28: 12 | D28: =B28/C28 -> 0

Sheet Тобол
A2: Тобол | B2: Всего на обсл. под. | C2: Кол-во под. по ук | D2: Кол-во абонентов | E2: Общая сумма | F2: кол-во мес | G2: р/аб | H2: Сумма за месяц | I2: Сумма расхода на УК
A3: ФОТ Воронцов | B3: ='Исходные данные'!D11 -> 214 | C3: ='Исходные данные'!F32 -> 8 | E3: 480420 | F3: 12 | H3: =E3/F3 -> 40035 | I3: =H3/B3*C3 -> 1496.6355
A4: ФОТ Балашев | B4: ='Исходные данные'!E13 -> 30 | C4: ='Исходные данные'!H32 -> 1 | E4: 305868 | F4: 12 | H4: =E4/F4 -> 25489 | I4: =H4/B4*C4 -> 849.63333
A5: Услуги УК | F5: 12 | H5: =E5/F5 -> 0 | I5: =H5 -> 0
A6: Интернет физ.лица | F6: 12 | H6: =E6/F6 -> 0 | I6: =H6 -> 0
A7: Оборудование (Сервис) | E7: 2190 | F7: 12 | H7: =E7/F7 -> 182.5 | I7: =H7 -> 182.5
A8: Оборудование (Кап.вложения) | E8: 0 | F8: 12 | H8: =E8/F8 -> 0 | I8: =H8 -> 0
A9: Оборудование (Модернизация) | E9: 0 | F9: 12 | H9: =E9/F9 -> 0 | I9: =H9 -> 0
A10: Расходники по УК | F10: 12 | H10: =E10/F10 -> 0 | I10: =H10 -> 0
A11: Транспортные по УК | F11: 12 | H11: =E11/F11 -> 0 | I11: =H11 -> 0
A12: Кап.вложения | H12: =D29 -> 0 | I12: =H12 -> 0
A13: Общие расходы ГЭ | D13: =B18+B19 -> 176 | G13: ='Общие расходы ГЭ'!G16 -> 9.1731977 | I13: =D13*G13 -> 1614.4828
A14: Общие расходы города | D14: =B18+B19 -> 176 | G14: ='Общие расходы г. Тюмень'!F4 -> 0.27439332 | I14: =D14*G14 -> 48.293225
A15: УСН | D15: =B18+B19 -> 176 | G15: ='Общие расходы г. Тюмень'!F30 -> 0.74801393 | I15: =D15*G15 -> 131.65045
A16: ИТОГО | I16: =SUM(I3:I15) -> 4323.1953
A18: Абонентов домофония | B18: ='Исходные данные'!B32 -> 88
A19: Абонентов ВН | B19: ='Исходные данные'!C32 -> 88
A20: Подъездов | B20: ='Исходные данные'!D25 -> 0
A22: КАП.ВЛОЖЕНИЯ
A23: Наименование | B23: Общая сумма | C23: кол-во мес | D23: Итого
A24: Монтажи фот | C24: 12 | D24: =B24/C24 -> 0
A25: подключение новой точки | C25: 12 | D25: =B25/C25 -> 0
B29: =SUM(B24:B28) -> 0 | C29: 12 | D29: =B29/C29 -> 0

Sheet Высота
A2: ВЫСОТА | B2: Всего на обсл. под. | C2: Кол-во под. по ук | D2: Кол-во абонентов | E2: Общая сумма | F2: кол-во мес | G2: р/аб | H2: Сумма за месяц | I2: Сумма расхода на УК
A3: ФОТ Полуянов | B3: ='Исходные данные'!D12 -> 402 | C3: ='Исходные данные'!G34 -> 33 | E3: 637618 | F3: 12 | H3: =E3/F3 -> 53134.833 | I3: =H3/B3*C3 -> 4361.8147
A4: ФОТ монтаж модер | E4: =10500+9000 -> 19500 | F4: 12 | H4: =E4/F4 -> 1625 | I4: =H4 -> 1625
A5: Интернет физ.лица | E5: =4750+1900 -> 6650 | F5: 12 | H5: =E5/F5 -> 554.16667 | I5: =H5 -> 554.16667
A6: Оборудование (Сервис) | E6: 1727 | F6: 12 | H6: =E6/F6 -> 143.91667 | I6: =H6 -> 143.91667
A7: Оборудование (Кап.вложения) | F7: 12 | H7: =E7/F7 -> 0 | I7: =H7 -> 0
A8: Оборудование (Модернизация) | E8: 13287 | F8: 12 | H8: =E8/F8 -> 1107.25 | I8: =H8 -> 1107.25
A9: Расходники по УК | F9: 12 | H9: =E9/F9 -> 0 | I9: =H9 -> 0
A10: Транспортные по УК | E10: 1169 | F10: 12 | H10: =E10/F10 -> 97.416667 | I10: =H10 -> 97.416667
A11: Кап.вложения | H11: =D28 -> 0 | I11: =H11 -> 0
A12: Общие расходы ГЭ | D12: =B17+B18 -> 554 | G12: ='Общие расходы ГЭ'!G16 -> 9.1731977 | I12: =D12*G12 -> 5081.9515
A13: Общие расходы города | D13: =B17+B18 -> 554 | G13: ='Общие расходы г. Тюмень'!F4 -> 0.27439332 | I13: =D13*G13 -> 152.0139
A14: УСН | D14: =B17+B18 -> 554 | G14: ='Общие расходы г. Тюмень'!F30 -> 0.74801393 | I14: =D14*G14 -> 414.39972
A15: ИТОГО | I15: =SUM(I3:I14) -> 13537.93
A17: Абонентов домофония | B17: ='Исходные данные'!B34 -> 554
A18: Абонентов ВН | B18: ='Исходные данные'!C34 -> 0
A19: Подъездов | B19: ='Исходные данные'!D25 -> 0
A21: КАП.ВЛОЖЕНИЯ
A22: Наименование | B22: Общая сумма | C22: кол-во мес | D22: Итого
A23: Монтажи фот | C23: 12 | D23: =B23/C23 -> 0
A24: подключение новой точки Малышева 24 | C24: 12 | D24: =B24/C24 -> 0
B28: =SUM(B23:B27) -> 0 | C28: 12 | D28: =B28/C28 -> 0

Sheet Электрон
A2: ЭЛЕКТРОН | B2: Всего на обсл. под. | C2: Кол-во под. по ук | D2: Кол-во абонентов | E2: Общая сумма | F2: кол-во мес | G2: р/аб | H2: Сумма за месяц | I2: Сумма расхода на УК
A3: ФОТ Воронцов | B3: ='Исходные данные'!D11 -> 214 | C3: 0 | E3: 480420 | F3: 12 | H3: =E3/F3 -> 40035 | I3: =H3/B3*C3 -> 0
A4: ФОТ Балашев | B4: ='Исходные данные'!E13 -> 30 | C4: ='Исходные данные'!H35 -> 1 | E4: 305868 | F4: 12 | H4: =E4/F4 -> 25489 | I4: =H4/B4*C4 -> 849.63333
A5: Услуги УК | F5: 12 | H5: =E5/F5 -> 0 | I5: =H5 -> 0
A6: Интернет физ.лица | E6: =1050+100 -> 1150 | F6: 12 | H6: =E6/F6 -> 95.833333 | I6: =H6 -> 95.833333
A7: Оборудование (Сервис) | E7: 554 | F7: 12 | H7: =E7/F7 -> 46.166667 | I7: =H7 -> 46.166667
A8: Оборудование (Кап.вложения) | E8: 177833 | F8: 12 | H8: =E8/F8 -> 14819.417 | I8: =H8 -> 14819.417
A9: Оборудование (Модернизация) | E9: 0 | F9: 12 | H9: =E9/F9 -> 0 | I9: =H9 -> 0
A10: Расходники по УК | F10: 12 | H10: =E10/F10 -> 0 | I10: =H10 -> 0
A11: Транспортные по УК | F11: 12 | H11: =E11/F11 -> 0 | I11: =H11 -> 0
A12: Кап.вложения | H12: =D29 -> 12360.333 | I12: =H12 -> 12360.333
A13: Общие расходы ГЭ | D13: =B18+B19 -> 564 | G13: ='Общие расходы ГЭ'!G16 -> 9.1731977 | I13: =D13*G13 -> 5173.6835
A14: Общие расходы города | D14: =B18+B19 -> 564 | G14: ='Общие расходы г. Тюмень'!F4 -> 0.27439332 | I14: =D14*G14 -> 154.75783
A15: УСН | D15: =B18+B19 -> 564 | G15: ='Общие расходы г. Тюмень'!F30 -> 0.74801393 | I15: =D15*G15 -> 421.87986
A16: ИТОГО | I16: =SUM(I3:I15) -> 33921.705
A18: Абонентов домофония | B18: ='Исходные данные'!B35 -> 282
A19: Абонентов ВН | B19: ='Исходные данные'!C35 -> 282
A20: Подъездов | B20: ='Исходные данные'!D25 -> 0
A22: КАП.ВЛОЖЕНИЯ
A23: Наименование | B23: Общая сумма | C23: кол-во мес | D23: Итого
A24: Монтажи фот | B24: 139000 | C24: 12 | D24: =B24/C24 -> 11583.333
A25: подключение новой точки | B25: 5000 | C25: 12 | D25: =B25/C25 -> 416.66667
A26: расходники | B26: 4324 | C26: 12 | D26: =B26/C26 -> 360.33333
B29: =SUM(B24:B28) -> 148324 | C29: 12 | D29: =B29/C29 -> 12360.333

Sheet Запад
A2: ЗАПАД | B2: Всего на обсл. под. | C2: Кол-во под. по ук | D2: Кол-во абонентов | E2: Общая сумма | F2: кол-во мес | G2: р/аб | H2: Сумма за месяц | I2: Сумма расхода на УК
A3: ФОТ Полуянов | B3: ='Исходные данные'!D12 -> 402 | C3: ='Исходные данные'!G25 -> 181 | E3: =637618+40000 -> 677618 | F3: 12 | H3: =E3/F3 -> 56468.167 | I3: =H3/B3*C3 -> 25424.722
A4: ФОТ Воронцов | B4: ='Исходные данные'!D11 -> 214 | C4: ='Исходные данные'!F25 -> 184 | E4: 480420 | F4: 12 | H4: =E4/F4 -> 40035 | I4: =H4/B4*C4 -> 34422.617
A5: ФОТ Балашев | B5: ='Исходные данные'!E13 -> 30 | C5: ='Исходные данные'!H25 -> 8 | E5: =305868+22000 -> 327868 | F5: 12 | H5: =E5/F5 -> 27322.333 | I5: =H5/B5*C5 -> 7285.9556
A6: Услуги УК | E6: 862850 | F6: 12 | H6: =E6/F6 -> 71904.167 | I6: =H6 -> 71904.167
A7: Интернет ЭРТХА | E7: 152554.27 | F7: 12 | H7: =E7/F7 -> 12712.856 | I7: =H7 -> 12712.856
A8: Интернет физ.лица | E8: =187779.93+1600 -> 189379.93 | F8: 12 | H8: =E8/F8 -> 15781.661 | I8: =H8 -> 15781.661
A9: Оборудование (Сервис) | E9: =200591+357+3000 -> 203948 | F9: 12 | H9: =E9/F9 -> 16995.667 | I9: =H9 -> 16995.667
A10: Оборудование (Кап.вложения) | E10: 133245 | F10: 12 | H10: =E10/F10 -> 11103.75 | I10: =H10 -> 11103.75
A11: Оборудование (Модернизация) | E11: 0 | F11: 12 | H11: =E11/F11 -> 0 | I11: =H11 -> 0
A12: ремонт шлагбаума | E12: =1500+6600 -> 8100 | F12: 12 | H12: =E12/F12 -> 675 | I12: =H12 -> 675
A13: расходники | F13: 12 | H13: =E13/F13 -> 0 | I13: =H13 -> 0
A14: сервис | F14: 12 | H14: =E14/F14 -> 0
A15: представительские | E15: 509 | F15: 12 | H15: =E15/F15 -> 42.416667 | I15: =H15 -> 42.416667
A16: Кап.вложения | H16: =D33 -> 17035.417 | I16: =H16 -> 17035.417
A17: Общие расходы ГЭ | D17: =B22+B23 -> 7406 | G17: ='Общие расходы ГЭ'!G16 -> 9.1731977 | I17: =D17*G17 -> 67936.702
A18: Общие расходы города | D18: =B22+B23 -> 7406 | G18: ='Общие расходы г. Тюмень'!F4 -> 0.27439332 | I18: =D18*G18 -> 2032.157
A19: УСН | D19: =B22+B23 -> 7406 | G19: ='Общие расходы г. Тюмень'!F30 -> 0.74801393 | I19: =D19*G19 -> 5539.7912
A20: ИТОГО | I20: =SUM(I3:I19) -> 288892.88
A22: Абонентов домофония | B22: ='Исходные данные'!B25 -> 6652
A23: Абонентов ВН | B23: ='Исходные данные'!C25 -> 754
A24: Подъездов | B24: ='Исходные данные'!D25 -> 0
A26: КАП.ВЛОЖЕНИЯ
A27: Наименование | B27: Общая сумма | C27: кол-во мес | D27: Итого
A28: Монтажи фот | B28: =18000+85000+8000+16500 -> 127500 | C28: 12 | D28: =B28/C28 -> 10625
A29: Поключение точки пархоменко 1 | B29: 8000 | C29: 12 | D29: =B29/C29 -> 666.66667
A30: подключение новых точек | B30: 40000 | C30: 12 | D30: =B30/C30 -> 3333.3333
A31: расходники на монтаж | B31: 28925 | C31: 12 | D31: =B31/C31 -> 2410.4167
B33: =SUM(B28:B32) -> 204425 | C33: 12 | D33: =B33/C33 -> 17035.417

Sheet Вавилон
A2: ВАВИЛОН | B2: Всего на обсл. под. | C2: Кол-во под. по ук | D2: Кол-во абонентов | E2: Общая сумма | F2: кол-во мес | G2: р/аб | H2: Сумма за месяц | I2: Сумма расхода на УК
A3: ФОТ Балашев | B3: 1 | E3: 0 | F3: 12 | H3: =E3/F3 -> 0 | I3: =H3/B3*C3 -> 0
A4: Услуги УК | F4: 12 | H4: =E4/F4 -> 0 | I4: =H4 -> 0
A5: Интернет физ.лица | E5: 3240 | F5: 12 | H5: =E5/F5 -> 270 | I5: =H5 -> 270
A6: Оборудование (Сервис) | E6: 0 | F6: 12 | H6: =E6/F6 -> 0 | I6: =H6 -> 0
A7: Оборудование (Кап.вложения) | E7: 0 | F7: 12 | H7: =E7/F7 -> 0 | I7: =H7 -> 0
A8: Оборудование (Модернизация) | E8: 0 | F8: 12 | H8: =E8/F8 -> 0 | I8: =H8 -> 0
A9: Расходники по УК | F9: 12 | H9: =E9/F9 -> 0 | I9: =H9 -> 0
A10: Транспортные по УК | F10: 12 | H10: =E10/F10 -> 0 | I10: =H10 -> 0
A11: Кап.вложения | H11: =D28 -> 2375 | I11: =H11 -> 2375
A12: Общие расходы ГЭ | D12: =B17+B18 -> 54 | G12: ='Общие расходы ГЭ'!G16 -> 9.1731977 | I12: =D12*G12 -> 495.35267
A13: Общие расходы города | D13: =B17+B18 -> 54 | G13: ='Общие расходы г. Тюмень'!F4 -> 0.27439332 | I13: =D13*G13 -> 14.817239
A14: УСН | D14: =B17+B18 -> 54 | G14: ='Общие расходы г. Тюмень'!F30 -> 0.74801393 | I14: =D14*G14 -> 40.392752
A15: ИТОГО | I15: =SUM(I3:I14) -> 3195.5627
A17: Абонентов домофония | B17: ='Исходные данные'!B36 -> 0
A18: Абонентов ВН | B18: ='Исходные данные'!C36 -> 54
A19: Подъездов | B19: ='Исходные данные'!D25 -> 0
A21: КАП.ВЛОЖЕНИЯ
A22: Наименование | B22: Общая сумма | C22: кол-во мес | D22: Итого
A23: Монтажи фот | B23: 20000 | C23: 12 | D23: =B23/C23 -> 1666.6667
A24: подкл новой точки | B24: 7500 | C24: 12 | D24: =B24/C24 -> 625
A25: расходники | B25: 1000 | C25: 12 | D25: =B25/C25 -> 83.333333
B28: =SUM(B23:B27) -> 28500 | C28: 12 | D28: =B28/C28 -> 2375

Sheet Юг
A2: ЗАПАД | B2: Всего на обсл. под. | C2: Кол-во под. по ук | D2: Кол-во абонентов | E2: Общая сумма | F2: кол-во мес | G2: р/аб | H2: Сумма за месяц | I2: Сумма расхода на УК
A3: ФОТ Олег | B3: ='Исходные данные'!D10 -> 276 | C3: ='Исходные данные'!E26 -> 1 | E3: 402810 | F3: 12 | H3: =E3/F3 -> 33567.5 | I3: =H3/B3*C3 -> 121.62138
A4: ФОТ Балашов | B4: ='Исходные данные'!E13 -> 30 | C4: ='Исходные данные'!H26 -> 2 | E4: 305868 | F4: 12 | H4: =E4/F4 -> 25489 | I4: =H4/B4*C4 -> 1699.2667
A5: Интернет | E5: 8475 | F5: 12 | H5: =E5/F5 -> 706.25 | I5: =H5 -> 706.25
A6: Оборудование (Сервис) | E6: 4000 | F6: 12 | H6: =E6/F6 -> 333.33333 | I6: =H6 -> 333.33333
A7: Оборудование (Кап.вложения) | E7: 0 | F7: 12 | H7: =E7/F7 -> 0 | I7: =H7 -> 0
A8: Оборудование (Модернизация) | E8: 0 | F8: 12 | H8: =E8/F8 -> 0 | I8: =H8 -> 0
A9: Транспортные | E9: 726 | F9: 12 | H9: =E9/F9 -> 60.5 | I9: =H9 -> 60.5
A10: Общие расходы ГЭ | D10: =B15+B16 -> 266 | G10: ='Общие расходы ГЭ'!G16 -> 9.1731977 | I10: =D10*G10 -> 2440.0706
A11: Общие расходы города | D11: =B15+B16 -> 266 | G11: ='Общие расходы г. Тюмень'!F4 -> 0.27439332 | I11: =D11*G11 -> 72.988624
A12: УСН | D12: =B15+B16 -> 266 | G12: ='Общие расходы г. Тюмень'!F30 -> 0.74801393 | I12: =D12*G12 -> 198.97171
A13: ИТОГО | I13: =SUM(I3:I12) -> 5633.0023
A15: Абонентов домофония | B15: ='Исходные данные'!B26 -> 43
A16: Абонентов ВН | B16: ='Исходные данные'!C26 -> 223
A17: Подъездов | B17: ='Исходные данные'!D26 -> 0
A19: КАП.ВЛОЖЕНИЯ
A20: Наименование | B20: Общая сумма | C20: кол-во мес | D20: Итого
C21: 12 | D21: =B21/C21 -> 0
C22: 12 | D22: =B22/C22 -> 0
D23: =SUM(D21) -> 0

Sheet Суходолье
A2: Суходолье | B2: Всего на обсл. под. | C2: Кол-во под. по ук | D2: Кол-во абонентов | E2: Общая сумма | F2: кол-во мес | G2: Сумма за месяц | H2: р/аб | I2: Сумма расхода на УК
A3: ФОТ Полуянов | B3: ='Исходные данные'!D12 -> 402 | C3: ='Исходные данные'!G22 -> 28 | E3: 637618 | F3: 12 | G3: =E3/F3 -> 53134.833 | I3: =G3/B3*C3 -> 3700.9337
A4: ФОТ | F4: 12 | G4: =E4/F4 -> 0 | I4: =G4 -> 0
A5: Интернет позитив | E5: 86400 | F5: 12 | G5: =E5/F5 -> 7200 | I5: =G5 -> 7200
A6: Оборудование (Сервис) | E6: 64643 | F6: 12 | G6: =E6/F6 -> 5386.9167 | I6: =G6 -> 5386.9167
A7: Оборудование (Кап.вложения) | E7: 0 | F7: 12 | G7: =E7/F7 -> 0 | I7: =G7 -> 0
A8: Оборудование (Модернизация) | E8: 0 | F8: 12 | G8: =E8/F8 -> 0 | I8: =G8 -> 0
A9: Расходники по УК | F9: 12 | G9: =E9/F9 -> 0 | I9: =G9 -> 0
A10: Транспортные по УК | E10: 533 | F10: 12 | G10: =E10/F10 -> 44.416667 | I10: =G10 -> 44.416667
A11: Кап.вложения | I11: =D23 -> 0
A12: Общие расходы ГЭ | D12: =B17 -> 3980 | H12: ='Общие расходы ГЭ'!G16 -> 9.1731977 | I12: =D12*H12 -> 36509.327
A13: Общие расходы по Тюмени | D13: =B17 -> 3980 | H13: ='Общие расходы г. Тюмень'!F4 -> 0.27439332 | I13: =D13*H13 -> 1092.0854
A14: УСН | D14: =B17 -> 3980 | H14: ='Общие расходы г. Тюмень'!F30 -> 0.74801393 | I14: =D14*H14 -> 2977.0955
A15: ИТОГО | I15: =SUM(I3:I14) -> 56910.775
A17: Абонентов домофония | B17: ='Исходные данные'!B22 -> 3980
A18: Абонентов ВН | B18: ='Исходные данные'!C22 -> 0
A19: Подъездов | B19: ='Исходные данные'!D22 -> 0
A21: КАП.ВЛОЖЕНИЯ
A22: Наименование | B22: Общая сумма | C22: кол-во мес | D22: Итого
C23: 12 | D23: =B23/C23 -> 0

Sheet Надежное управление
A2: Надежное управление | B2: Всего на обсл. под. | C2: Кол-во под. по ук | D2: Кол-во абонентов | E2: Общая сумма | F2: кол-во мес | G2: Сумма за месяц | H2: р/аб | I2: Сумма расхода на УК
A3: ФОТ Полуянов | B3: ='Исходные данные'!D12 -> 402 | C3: ='Исходные данные'!G17 -> 5 | E3: 637618 | F3: 12 | G3: =E3/F3 -> 53134.833 | I3: =G3/B3*C3 -> 660.88101
F5: 12 | G5: =E5/F5 -> 0 | I5: =G5 -> 0
A6: Оборудование (Сервис) | E6: 535 | F6: 12 | G6: =E6/F6 -> 44.583333 | I6: =G6 -> 44.583333
A7: Оборудование (Кап.вложения) | E7: 0 | F7: 12 | G7: =E7/F7 -> 0 | I7: =G7 -> 0
A8: Оборудование (Модернизация) | E8: 0 | F8: 12 | G8: =E8/F8 -> 0 | I8: =G8 -> 0
A9: Расходники по УК | E9: 350 | F9: 12 | G9: =E9/F9 -> 29.166667 | I9: =G9 -> 29.166667
A10: Общие расходы ГЭ | D10: =B15 -> 220 | H10: ='Общие расходы ГЭ'!G16 -> 9.1731977 | I10: =D10*H10 -> 2018.1035
A11: Общие расходы по Тюмени | D11: =B15 -> 220 | H11: ='Общие расходы г. Тюмень'!F4 -> 0.27439332 | I11: =D11*H11 -> 60.366531
A12: УСН | D12: =B15 -> 220 | H12: ='Общие расходы г. Тюмень'!F30 -> 0.74801393 | I12: =D12*H12 -> 164.56307
I13: =SUM(I3:I12) -> 2977.6641
A15: Абонентов домофония | B15: ='Исходные данные'!B17 -> 220
A16: Абонентов ВН | B16: ='Исходные данные'!C17 -> 0
A17: Подъездов | B17: ='Исходные данные'!D17 -> 0
A19: КАП.ВЛОЖЕНИЯ
A20: Наименование | B20: Общая сумма | C20: кол-во мес | D20: Итого

Sheet УК линейная
A2: Линейная | B2: Всего на обсл. под. | C2: Кол-во под. по ук | D2: Кол-во абонентов | E2: Общая сумма | F2: кол-во мес | G2: Сумма за месяц | H2: р/аб | I2: Сумма расхода на УК
A3: ФОТ Полуянов | B3: ='Исходные данные'!D12 -> 402 | C3: ='Исходные данные'!G18 -> 8 | E3: 637618 | F3: 12 | G3: =E3/F3 -> 53134.833 | I3: =G3/B3*C3 -> 1057.4096
A4: Оборудование (Сервис) | E4: 2565 | F4: 12 | G4: =E4/F4 -> 213.75 | I4: =G4 -> 213.75
A5: Оборудование (Кап.вложения) | E5: 0 | F5: 12 | G5: =E5/F5 -> 0 | I5: =G5 -> 0
A6: Оборудование (Модернизация) | E6: 0 | F6: 12 | G6: =E6/F6 -> 0 | I6: =G6 -> 0
A7: Расходники по Ук | F7: 12 | G7: =E7/F7 -> 0 | I7: =G7 -> 0
A8: Общие расходы ГЭ | D8: =B13 -> 392 | H8: ='Общие расходы ГЭ'!G16 -> 9.1731977 | I8: =D8*H8 -> 3595.8935
A9: Общие расходы по Тюмени | D9: =B13 -> 392 | H9: ='Общие расходы г. Тюмень'!F4 -> 0.27439332 | I9: =D9*H9 -> 107.56218
A10: УСН | D10: =B13 -> 392 | H10: ='Общие расходы г. Тюмень'!F30 -> 0.74801393 | I10: =D10*H10 -> 293.22146
A11: ИТОГО | I11: =SUM(I3:I10) -> 5267.8367
A13: Абонентов домофония | B13: ='Исходные данные'!B18 -> 392
A14: Абонентов ВН | B14: ='Исходные данные'!C18 -> 0
A15: Подъездов | B15: ='Исходные данные'!D18 -> 0
A17: КАП.ВЛОЖЕНИЯ
A18: Наименование | B18: Общая сумма | C18: кол-во мес | D18: Итого

Sheet ЖЭУ 9
A2: ЖЭУ 9 | B2: Всего на обсл. под. | C2: Кол-во под. по ук | D2: Кол-во абонентов | E2: Общая сумма | F2: кол-во мес | G2: Сумма за месяц | H2: р/аб | I2: Сумма расхода на УК
A3: ФОТ Полуянов | B3: ='Исходные данные'!D12 -> 402 | C3: ='Исходные данные'!G24 -> 18 | E3: 637618 | F3: 12 | G3: =E3/F3 -> 53134.833 | I3: =G3/B3*C3 -> 2379.1716
A4: ФОТ | F4: 12 | G4: =E4/F4 -> 0 | I4: =G4 -> 0
A5: Оборудование (Сервис) | E5: =15304+40 -> 15344 | F5: 12 | G5: =E5/F5 -> 1278.6667 | I5: =G5 -> 1278.6667
A6: Оборудование (Кап.вложения) | E6: 37807 | F6: 12 | G6: =E6/F6 -> 3150.5833 | I6: =G6 -> 3150.5833
A7: Оборудование (Модернизация) | E7: 0 | F7: 12 | G7: =E7/F7 -> 0 | I7: =G7 -> 0
A8: Расходники по УК | F8: 12 | G8: =E8/F8 -> 0 | I8: =G8 -> 0
A9: Интернет | E9: 10339 | F9: 12 | G9: =E9/F9 -> 861.58333 | I9: =G9 -> 861.58333
A10: Кап.вложения | G10: =D26 -> 0 | I10: =G10 -> 0
A11: Общие расходы ГЭ | D11: =B16 -> 1298 | H11: ='Общие расходы ГЭ'!G16 -> 9.1731977 | I11: =D11*H11 -> 11906.811
A12: Общие расходы по Тюмени | D12: =B16 -> 1298 | H12: ='Общие расходы г. Тюмень'!F4 -> 0.27439332 | I12: =D12*H12 -> 356.16253
A13: УСН | D13: =B16 -> 1298 | H13: ='Общие расходы г. Тюмень'!F30 -> 0.74801393 | I13: =D13*H13 -> 970.92209
A14: ИТОГО | I14: =SUM(I3:I13) -> 20903.9
A16: Абонентов домофония | B16: ='Исходные данные'!B24 -> 1298
A17: Абонентов ВН | B17: ='Исходные данные'!C24 -> 0
A18: Подъездов | B18: ='Исходные данные'!D24 -> 0
A20: КАП.ВЛОЖЕНИЯ
A21: Наименование | B21: Общая сумма | C21: кол-во мес | D21: Итого
A22: Монтажи фот | C22: 12
C23: 12
D26: =SUM(D22:D25) -> 0

Sheet УК на Ткацком
A2: Ук на Ткацком | B2: Всего на обсл. под. | C2: Кол-во под. по ук | D2: Кол-во абонентов | E2: Общая сумма | F2: кол-во мес | G2: Сумма за месяц | H2: р/аб | I2: Сумма расхода на УК
A3: ФОТ Полуянов | B3: ='Исходные данные'!D12 -> 402 | C3: ='Исходные данные'!G21 -> 4 | E3: 637618 | F3: 12 | G3: =E3/F3 -> 53134.833 | I3: =G3/B3*C3 -> 528.70481
A4: Оборудование (Сервис) | E4: 0 | F4: 12 | G4: =E4/F4 -> 0
A5: Оборудование (Кап.вложения) | E5: 0 | F5: 12 | G5: =E5/F5 -> 0
A6: Оборудование (Модернизация) | E6: 0 | F6: 12 | G6: =E6/F6 -> 0
A7: интернет | E7: 599 | F7: 12 | G7: =E7/F7 -> 49.916667 | I7: =D23 -> 3333.3333
A8: Общие расходы ГЭ | D8: =B13 -> 339 | H8: ='Общие расходы ГЭ'!G16 -> 9.1731977 | I8: =D8*H8 -> 3109.714
A9: Общие расходы по Тюмени | D9: =B13 -> 339 | H9: ='Общие расходы г. Тюмень'!F4 -> 0.27439332 | I9: =D9*H9 -> 93.019337
A10: УСН | D10: =B13 -> 339 | H10: ='Общие расходы г. Тюмень'!F30 -> 0.74801393 | I10: =D10*H10 -> 253.57672
A11: ИТОГО | I11: =SUM(I3:I10) -> 7318.3482
A13: Абонентов домофония | B13: ='Исходные данные'!B21 -> 339
A14: Абонентов ВН | B14: ='Исходные данные'!C21 -> 0
A15: Подъездов | B15: ='Исходные данные'!D21 -> 0
A17: КАП.ВЛОЖЕНИЯ
A18: Наименование | B18: Общая сумма | C18: кол-во мес | D18: Итого
A19: ФОТ монтажи | B19: 40000 | C19: 12 | D19: =B19/C19 -> 3333.3333
A20: подключение новой точки | B20: 8000
D23: =SUM(D19:D22) -> 3333.3333

Sheet УК на пражской
A2: УК на пражской | B2: Всего на обсл. под. | C2: Кол-во под. по ук | D2: Кол-во абонентов | E2: Общая сумма | F2: кол-во мес | G2: Сумма за месяц | H2: р/аб | I2: Сумма расхода на УК
A3: ФОТ Полуянов | B3: ='Исходные данные'!D12 -> 402 | C3: ='Исходные данные'!G19 -> 100 | E3: 637618 | F3: 12 | G3: =E3/F3 -> 53134.833 | I3: =G3/B3*C3 -> 13217.62
A4: ФОТ Балашов | B4: ='Исходные данные'!E13 -> 30 | C4: ='Исходные данные'!H19 -> 1 | E4: 305868 | F4: 12 | G4: =E4/F4 -> 25489 | I4: =G4/B4*C4 -> 849.63333
A5: Интернет физ.лица | E5: 57191 | F5: 12 | G5: =E5/F5 -> 4765.9167 | I5: =G5 -> 4765.9167
A6: Оборудование (Сервис) | E6: 112265 | F6: 12 | G6: =E6/F6 -> 9355.4167 | I6: =G6 -> 9355.4167
A7: Оборудование (Кап.вложения) | E7: 0 | F7: 12 | G7: =E7/F7 -> 0 | I7: =G7 -> 0
A8: Оборудование (Модернизация) | E8: 27493 | F8: 12 | G8: =E8/F8 -> 2291.0833 | I8: =G8 -> 2291.0833
A9: сварка | E9: 1000 | F9: 12 | G9: =E9/F9 -> 83.333333
A10: Кап.вложение | I10: =D27 -> 0
A11: Транспортные | E11: 1173 | F11: 12 | G11: =E11/F11 -> 97.75 | I11: =G11 -> 97.75
A12: Общие расходы ГЭ | D12: =B17 -> 1720 | H12: ='Общие расходы ГЭ'!G16 -> 9.1731977 | I12: =D12*H12 -> 15777.9
A13: Общие расходы по Тюмени | D13: =B17 -> 1720 | H13: ='Общие расходы г. Тюмень'!F4 -> 0.27439332 | I13: =D13*H13 -> 471.95652
A14: УСН | D14: =B17 -> 1720 | H14: ='Общие расходы г. Тюмень'!F30 -> 0.74801393 | I14: =D14*H14 -> 1286.584
A15: ИТОГО | I15: =SUM(I3:I14) -> 48113.861
A17: Абонентов домофония | B17: ='Исходные данные'!B19 -> 1720
A18: Абонентов ВН | B18: ='Исходные данные'!C19 -> 77
A19: Подъездов | B19: ='Исходные данные'!D19 -> 0
A21: КАП.ВЛОЖЕНИЯ
A22: Наименование | B22: Общая сумма | C22: кол-во мес | D22: Итого
A23: Монтаж фот | C23: 12 | D23: =B23/C23 -> 0
A24: подключение новых точек | C24: 12 | D24: =B24/C24 -> 0
A25: за согласование вн | C25: 12 | D25: =B25/C25 -> 0
D27: =SUM(D23:D26) -> 0

Sheet ЖСУ
A2: ЖСУ | B2: Всего на обсл. под. | C2: Кол-во под. по ук | D2: Кол-во абонентов | E2: Общая сумма | F2: кол-во мес | G2: Сумма за месяц | H2: р/аб | I2: Сумма расхода на УК
A3: ФОТ Олег | B3: ='Исходные данные'!D10 -> 276 | C3: ='Исходные данные'!E16 -> 232 | E3: 402810 | F3: 12 | G3: =E3/F3 -> 33567.5 | I3: =G3/B3*C3 -> 28216.159
A4: ФОТ Балашов | B4: ='Исходные данные'!E13 -> 30 | C4: ='Исходные данные'!H16 -> 2 | E4: 305868 | F4: 12 | G4: =E4/F4 -> 25489 | I4: =G4/B4*C4 -> 1699.2667
A5: Интернет ЭРТХ | E5: 86738.32 | F5: 12 | G5: =E5/F5 -> 7228.1933 | I5: =G5 -> 7228.1933
A6: Интернет физ.лица | E6: =70501.94+11000+4793 -> 86294.94 | F6: 12 | G6: =E6/F6 -> 7191.245 | I6: =G6 -> 7191.245
A7: Оборудование (Сервис) | E7: 128366 | F7: 12 | G7: =E7/F7 -> 10697.167 | I7: =G7 -> 10697.167
A8: Оборудование (Кап.вложения) | E8: 0 | F8: 12 | G8: =E8/F8 -> 0 | I8: =G8 -> 0
A9: Оборудование (Модернизация) | E9: 0 | F9: 12 | G9: =E9/F9 -> 0 | I9: =G9 -> 0
A10: Расходники по УК | F10: 12 | G10: =E10/F10 -> 0 | I10: =G10 -> 0
A11: кап.вложения | G11: =D24 -> 0 | I11: =D28 -> 2833.3333
A12: Транспортные по УК | F12: 12 | G12: =E12/F12 -> 0 | I12: =G12 -> 0
A13: Общие расходы ГЭ | D13: =B18+B19 -> 4110 | H13: ='Общие расходы ГЭ'!G16 -> 9.1731977 | I13: =D13*H13 -> 37701.842
A14: Общие расходы по Тюмени | D14: =B18+B19 -> 4110 | H14: ='Общие расходы г. Тюмень'!F4 -> 0.27439332 | I14: =D14*H14 -> 1127.7566
A15: УСН | D15: =B18+B19 -> 4110 | H15: ='Общие расходы г. Тюмень'!F30 -> 0.74801393 | I15: =D15*H15 -> 3074.3373
I16: =SUM(I3:I15) -> 99769.301
A18: Абонентов домофония | B18: ='Исходные данные'!B16 -> 4024
A19: Абонентов ВН | B19: ='Исходные данные'!C16 -> 86
A20: Подъездов | B20: ='Исходные данные'!D16 -> 0
A22: КАП.ВЛОЖЕНИЯ
A23: Наименование | B23: Общая сумма | C23: кол-во мес | D23: Итого
A24: Монтаж фот | C24: 12 | D24: =B24/C24 -> 0
A25: подключение новой точки | B25: =24000+10000 -> 34000 | C25: 12 | D25: =B25/C25 -> 2833.3333
D28: =SUM(D24:D27) -> 2833.3333

Sheet Восток сити
A2: ЖСУ | B2: Всего на обсл. под. | C2: Кол-во под. по ук | D2: Кол-во абонентов | E2: Общая сумма | F2: кол-во мес | G2: Сумма за месяц | H2: р/аб | I2: Сумма расхода на УК
A3: ФОТ Полуянов | B3: ='Исходные данные'!D12 -> 402 | C3: ='Исходные данные'!G29 -> 2 | E3: 637618 | F3: 12 | G3: =E3/F3 -> 53134.833 | I3: =G3/B3*C3 -> 264.3524
A4: ФОТ Балашов | B4: ='Исходные данные'!E13 -> 30 | C4: ='Исходные данные'!H29 -> 1 | E4: 305868 | F4: 12 | G4: =E4/F4 -> 25489 | I4: =G4/B4*C4 -> 849.63333
A5: Интернет | E5: 8180 | F5: 12 | G5: =E5/F5 -> 681.66667 | I5: =G5 -> 681.66667
F6: 12 | G6: =E6/F6 -> 0 | I6: =G6 -> 0
A7: Оборудование (Сервис) | E7: 10562 | F7: 12 | G7: =E7/F7 -> 880.16667 | I7: =G7 -> 880.16667
A8: Оборудование (Кап.вложения) | E8: 3180 | F8: 12 | G8: =E8/F8 -> 265 | I8: =G8 -> 265
A9: Оборудование (Модернизация) | E9: 0 | F9: 12 | G9: =E9/F9 -> 0 | I9: =G9 -> 0
A10: Расходники по УК | F10: 12 | G10: =E10/F10 -> 0 | I10: =G10 -> 0
A11: кап.вложения | I11: =D28 -> 291.66667
A12: Транспортные по УК | F12: 12 | G12: =E12/F12 -> 0 | I12: =G12 -> 0
A13: Общие расходы ГЭ | D13: =B18+B19 -> 144 | H13: ='Общие расходы ГЭ'!G16 -> 9.1731977 | I13: =D13*H13 -> 1320.9405
A14: Общие расходы по Тюмени | D14: =B18+B19 -> 144 | H14: ='Общие расходы г. Тюмень'!F4 -> 0.27439332 | I14: =D14*H14 -> 39.512639
A15: УСН | D15: =B18+B19 -> 144 | H15: ='Общие расходы г. Тюмень'!F30 -> 0.74801393 | I15: =D15*H15 -> 107.71401
I16: =SUM(I3:I15) -> 4700.6528
A18: Абонентов домофония | B18: ='Исходные данные'!B29 -> 72
A19: Абонентов ВН | B19: ='Исходные данные'!C29 -> 72
A20: Подъездов | B20: ='Исходные данные'!D29 -> 0
A22: КАП.ВЛОЖЕНИЯ
A23: Наименование | B23: Общая сумма | C23: кол-во мес | D23: Итого
A24: Монтаж фот | B24: 3500 | C24: 12 | D24: =B24/C24 -> 291.66667
C25: 12 | D25: =B25/C25 -> 0
D28: =SUM(D24:D27) -> 291.66667

Sheet Аурика 
A2: ЖСУ | B2: Всего на обсл. под. | C2: Кол-во под. по ук | D2: Кол-во абонентов | E2: Общая сумма | F2: кол-во мес | G2: Сумма за месяц | H2: р/аб | I2: Сумма расхода на УК
A3: ФОТ Полуянов | B3: ='Исходные данные'!D12 -> 402 | C3: ='Исходные данные'!G20 -> 14 | E3: 637618 | F3: 12 | G3: =E3/F3 -> 53134.833 | I3: =G3/B3*C3 -> 1850.4668
A4: ФОТ | F4: 12 | G4: =E4/F4 -> 0 | I4: =G4 -> 0
A5: Интернет | E5: 15792 | F5: 12 | G5: =E5/F5 -> 1316 | I5: =G5 -> 1316
F6: 12 | G6: =E6/F6 -> 0 | I6: =G6 -> 0
A7: Оборудование (Сервис) | E7: 80624 | F7: 12 | G7: =E7/F7 -> 6718.6667 | I7: =G7 -> 6718.6667
A8: Оборудование (Кап.вложения) | E8: 0 | F8: 12 | G8: =E8/F8 -> 0 | I8: =G8 -> 0
A9: Оборудование (Модернизация) | E9: 0 | F9: 12 | G9: =E9/F9 -> 0 | I9: =G9 -> 0
A10: Расходники по УК | F10: 12 | G10: =E10/F10 -> 0 | I10: =G10 -> 0
A11: кап.вложения | I11: =D24 -> 0
A12: Транспортные по УК | E12: 580 | F12: 12 | G12: =E12/F12 -> 48.333333 | I12: =G12 -> 48.333333
A13: Общие расходы ГЭ | D13: =B18+B19 -> 514 | H13: ='Общие расходы ГЭ'!G16 -> 9.1731977 | I13: =D13*H13 -> 4715.0236
A14: Общие расходы по Тюмени | D14: =B18+B19 -> 514 | H14: ='Общие расходы г. Тюмень'!F4 -> 0.27439332 | I14: =D14*H14 -> 141.03817
A15: УСН | D15: =B18+B19 -> 514 | H15: ='Общие расходы г. Тюмень'!F30 -> 0.74801393 | I15: =D15*H15 -> 384.47916
I16: =SUM(I3:I15) -> 15174.008
A18: Абонентов домофония | B18: ='Исходные данные'!B20 -> 514
A19: Абонентов ВН | B19: ='Исходные данные'!C20 -> 0
A20: Подъездов | B20: ='Исходные данные'!D20 -> 0
A22: КАП.ВЛОЖЕНИЯ
A23: Наименование | B23: Общая сумма | C23: кол-во мес | D23: Итого

Sheet УК на Полевой
A2: ЖСУ | B2: Всего на обсл. под. | C2: Кол-во под. по ук | D2: Кол-во абонентов | E2: Общая сумма | F2: кол-во мес | G2: Сумма за месяц | H2: р/аб | I2: Сумма расхода на УК
A3: ФОТ Воронцов | B3: ='Исходные данные'!D11 -> 214 | C3: ='Исходные данные'!F30 -> 1 | E3: 480420 | F3: 12 | G3: =E3/F3 -> 40035 | I3: =G3/B3*C3 -> 187.07944
A4: ФОТ Балашов | B4: ='Исходные данные'!E13 -> 30 | C4: ='Исходные данные'!H30 -> 1 | E4: 305868 | F4: 12 | G4: =E4/F4 -> 25489 | I4: =G4/B4*C4 -> 849.63333
A5: Интернет ЭРТХ | F5: 12 | G5: =E5/F5 -> 0 | I5: =G5 -> 0
A6: Интернет фл | E6: 7511.62 | F6: 12 | G6: =E6/F6 -> 625.96833 | I6: =G6 -> 625.96833
A7: Оборудование (Сервис) | E7: 535 | F7: 12 | G7: =E7/F7 -> 44.583333 | I7: =G7 -> 44.583333
A8: Оборудование (Кап.вложения) | E8: 0 | F8: 12 | G8: =E8/F8 -> 0 | I8: =G8 -> 0
A9: Оборудование (Модернизация) | E9: 0 | F9: 12 | G9: =E9/F9 -> 0 | I9: =G9 -> 0
A10: Расходники по УК | F10: 12 | G10: =E10/F10 -> 0 | I10: =G10 -> 0
A11: кап.вложения | I11: =D24 -> 0
A12: Транспортные по УК | F12: 12 | G12: =E12/F12 -> 0 | I12: =G12 -> 0
A13: Общие расходы ГЭ | D13: =B18+B19 -> 180 | H13: ='Общие расходы ГЭ'!G16 -> 9.1731977 | I13: =D13*H13 -> 1651.1756
A14: Общие расходы по Тюмени | D14: =B18+B19 -> 180 | H14: ='Общие расходы г. Тюмень'!F4 -> 0.27439332 | I14: =D14*H14 -> 49.390798
A15: УСН | D15: =B18+B19 -> 180 | H15: ='Общие расходы г. Тюмень'!F30 -> 0.74801393 | I15: =D15*H15 -> 134.64251
I16: =SUM(I3:I15) -> 3542.4733
A18: Абонентов домофония | B18: ='Исходные данные'!B30 -> 90
A19: Абонентов ВН | B19: ='Исходные данные'!C30 -> 90
A20: Подъездов | B20: ='Исходные данные'!D30 -> 0
A22: КАП.ВЛОЖЕНИЯ
A23: Наименование | B23: Общая сумма | C23: кол-во мес | D23: Итого
A24: монтаж фот | C24: 12 | D24: =B24/C24 -> 0

Sheet Ирида
B2: Всего на обсл. под. | C2: Кол-во под. по ук | D2: Кол-во абонентов | E2: Общая сумма | F2: кол-во мес | G2: р/аб | H2: Сумма за месяц | I2: Сумма расхода на УК
A3: ФОТ Олег | B3: ='Исходные данные'!D10 -> 276 | C3: ='Исходные данные'!E28 -> 36 | E3: 402810 | F3: 12 | H3: =E3/F3 -> 33567.5 | I3: =H3/B3*C3 -> 4378.3696
A4: ФОТ Балашов | B4: ='Исходные данные'!E13 -> 30 | C4: ='Исходные данные'!H28 -> 3 | E4: 305868 | F4: 12 | H4: =E4/F4 -> 25489 | I4: =H4/B4*C4 -> 2548.9
A5: ФОТ | F5: 12 | H5: =E5/F5 -> 0 | I5: =H5 -> 0
A6: Оборудование (Сервис) | E6: =15256+16850 -> 32106 | F6: 12 | H6: =E6/F6 -> 2675.5 | I6: =H6 -> 2675.5
A7: Оборудование (Кап.вложения) | E7: 0 | F7: 12 | H7: =E7/F7 -> 0 | I7: =H7 -> 0
A8: Оборудование (Модернизация) | E8: 0 | F8: 12 | H8: =E8/F8 -> 0 | I8: =H8 -> 0
A9: Воров 27 восстан линии | E9: 2000 | F9: 12 | H9: =E9/F9 -> 166.66667 | I9: =H9 -> 166.66667
A10: Транспортные по УК | E10: 844 | F10: 12 | H10: =E10/F10 -> 70.333333 | I10: =H10 -> 70.333333
A11: Интернет | E11: 27365 | F11: 12 | H11: =E11/F11 -> 2280.4167 | I11: =H11 -> 2280.4167
A12: Кап.вложения | H12: =D28 -> 0 | I12: =H12 -> 0
A13: Общие расходы ГЭ | D13: =B18+B19 -> 1476 | G13: ='Общие расходы ГЭ'!G16 -> 9.1731977 | I13: =D13*G13 -> 13539.64
A14: Общие расходы города | D14: =B18+B19 -> 1476 | G14: ='Общие расходы г. Тюмень'!F4 -> 0.27439332 | I14: =D14*G14 -> 405.00455
A15: УСН | D15: =B18+B19 -> 1476 | G15: ='Общие расходы г. Тюмень'!F30 -> 0.74801393 | I15: =D15*G15 -> 1104.0686
A16: ИТОГО | I16: =SUM(I3:I15) -> 27168.899
A18: Абонентов домофония | B18: ='Исходные данные'!B28 -> 997
A19: Абонентов ВН | B19: ='Исходные данные'!C28 -> 479
A20: Подъездов | B20: ='Исходные данные'!D28 -> 0
A22: КАП.ВЛОЖЕНИЯ
A23: Наименование | B23: Общая сумма | C23: кол-во мес | D23: Итого
A24: Монтажи фот | C24: 12 | D24: =B24/C24 -> 0
A25: подключение новой точки | C25: 12 | D25: =B25/C25 -> 0
B28: =SUM(B24:B27) -> 0 | C28: 12 | D28: =SUM(D24:D27) -> 0

Sheet ТЭСК
A2: ТЭСК | B2: Всего на обсл. под. | C2: Кол-во под. по ук | D2: Кол-во абонентов | E2: Общая сумма | F2: кол-во мес | G2: Сумма за месяц | H2: р/аб | I2: Сумма расхода на УК
A3: ФОТ Олег | B3: ='Исходные данные'!D10 -> 276 | C3: ='Исходные данные'!E23 -> 2 | E3: 402810 | F3: 12 | G3: =E3/F3 -> 33567.5 | I3: =G3/B3*C3 -> 243.24275
A4: ФОТ Воронцов | B4: ='Исходные данные'!D11 -> 214 | C4: ='Исходные данные'!F23 -> 5 | E4: 480420 | F4: 12 | G4: =E4/F4 -> 40035 | I4: =G4/B4*C4 -> 935.3972
A5: ФОТ Балашов | B5: ='Исходные данные'!E13 -> 30 | C5: ='Исходные данные'!H23 -> 1 | E5: 305868 | F5: 12 | G5: =E5/F5 -> 25489 | I5: =G5/B5*C5 -> 849.63333
A6: Оборудование (Сервис) | E6: 13640 | F6: 12 | G6: =E6/F6 -> 1136.6667 | I6: =G6 -> 1136.6667
A7: Оборудование (Кап.вложения) | E7: 45178 | F7: 12 | G7: =E7/F7 -> 3764.8333 | I7: =G7 -> 3764.8333
A8: Оборудование (Модернизация) | E8: 0 | F8: 12 | G8: =E8/F8 -> 0 | I8: =G8 -> 0
A9: Транспортные | E9: 304 | F9: 12 | G9: =E9/F9 -> 25.333333 | I9: =G9 -> 25.333333
A10: Ка.вложения | I10: =D27 -> 2262.4167
A11: Интернет | E11: 5188.93 | F11: 12 | G11: =E11/F11 -> 432.41083 | I11: =G11 -> 432.41083
A12: Общие расходы ГЭ | D12: =B17 -> 436 | H12: ='Общие расходы ГЭ'!G16 -> 9.1731977 | I12: =D12*H12 -> 3999.5142
A13: Общие расходы по Тюмени | D13: =B17 -> 436 | H13: ='Общие расходы г. Тюмень'!F4 -> 0.27439332 | I13: =D13*H13 -> 119.63549
A14: УСН | D14: =B17 -> 436 | H14: ='Общие расходы г. Тюмень'!F30 -> 0.74801393 | I14: =D14*H14 -> 326.13408
I15: =SUM(I3:I14) -> 14095.218
E16: 5188.93
A17: Абонентов домофония | B17: 436
A18: Абонентов ВН | B18: 0
A19: Подъездов | B19: 5
A21: КАП.ВЛОЖЕНИЯ
A22: Наименование | B22: Общая сумма | C22: кол-во мес | D22: Итого
A23: ФОТ | B23: 16000 | C23: 12 | D23: =B23/C23 -> 1333.3333
A24: подключ новой точки | B24: =10000+1149 -> 11149 | C24: 12 | D24: =B24/C24 -> 929.08333
D27: =SUM(D23:D26) -> 2262.4167

Sheet Ладья
A2: Ладья | B2: Всего на обсл. под. | C2: Кол-во под. по ук | D2: Кол-во абонентов | E2: Общая сумма | F2: кол-во мес | G2: Сумма за месяц | H2: р/аб | I2: Сумма расхода на УК
A3: ФОТ Воронцов | B3: ='Исходные данные'!D11 -> 214 | C3: ='Исходные данные'!F27 -> 8 | E3: 480420 | F3: 12 | G3: =E3/F3 -> 40035 | I3: =G3/B3*C3 -> 1496.6355
A4: интернет | E4: 9100 | F4: 12 | G4: =E4/F4 -> 758.33333 | I4: =G4 -> 758.33333
A5: Оборудование (Сервис) | E5: 18455 | F5: 12 | G5: =E5/F5 -> 1537.9167 | I5: =G5 -> 1537.9167
A6: Оборудование (Кап.вложения) | E6: 0 | F6: 12 | G6: =E6/F6 -> 0 | I6: =G6 -> 0
A7: Оборудование (Модернизация) | E7: 0 | F7: 12 | G7: =E7/F7 -> 0 | I7: =G7 -> 0
A8: Оборудование по УК | F8: 12 | G8: =E8/F8 -> 0 | I8: =G8 -> 0
A9: Общие расходы ГЭ | D9: =B14 -> 286 | H9: ='Общие расходы ГЭ'!G16 -> 9.1731977 | I9: =D9*H9 -> 2623.5345
A10: Общие расходы по Тюмени | D10: =B14 -> 286 | H10: ='Общие расходы г. Тюмень'!F4 -> 0.27439332 | I10: =D10*H10 -> 78.476491
A11: УСН | D11: =B14 -> 286 | H11: ='Общие расходы г. Тюмень'!F30 -> 0.74801393 | I11: =D11*H11 -> 213.93199
A12: ИТОГО | I12: =SUM(I3:I11) -> 6708.8285
A14: Абонентов домофония | B14: ='Исходные данные'!B27 -> 286
A15: Абонентов ВН | B15: ='Исходные данные'!C27 -> 0
A16: Подъездов | B16: ='Исходные данные'!D27 -> 0
A18: КАП.ВЛОЖЕНИЯ
A19: Наименование | B19: Общая сумма | C19: кол-во мес | D19: Итого

Sheet Алсу
A2: Алсу | B2: Всего на обсл. под./камер | C2: Кол-во под. по ук | D2: Кол-во абонентов | E2: Общая сумма | F2: р/аб | G2: кол-во мес | H2: Сумма за месяц | I2: Сумма расхода на УК
A3: ФОТ Васильев | B3: ='Исходные данные'!D43 -> 334 | C3: ='Исходные данные'!D40 -> 229 | E3: =55500+13200+278297 -> 346997 | G3: 12 | H3: =E3/G3 -> 28916.417 | I3: =H3/B3*C3 -> 19825.926
A4: ФОТ Касимов | B4: ='Исходные данные'!E43 -> 499 | C4: ='Исходные данные'!E40 -> 437 | E4: =9000+82000+695981 -> 786981 | G4: 12 | H4: =E4/G4 -> 65581.75 | I4: =H4/B4*C4 -> 57433.316
A5: Интернет физ.лица | E5: =251513+3398+790 -> 255701 | G5: 12 | H5: =E5/G5 -> 21308.417 | I5: =H5 -> 21308.417
A6: Оборудование (Сервис) | E6: =319016+5430 -> 324446 | G6: 12 | H6: =E6/G6 -> 27037.167 | I6: =H6 -> 27037.167
A7: Оборудование (Кап.вложения) | E7: 102100 | G7: 12 | H7: =E7/G7 -> 8508.3333 | I7: =H7 -> 8508.3333
A8: Оборудование (Модернизация) | E8: 80693 | G8: 12 | H8: =E8/G8 -> 6724.4167 | I8: =H8 -> 6724.4167
A9: Расходники по Ук | E9: =468+818+1371+513+2746+4000+1299 -> 11215 | G9: 12 | H9: =E9/G9 -> 934.58333 | I9: =H9 -> 934.58333
A10: Доп.работа+монтажные работы | G10: 12 | H10: =E10/G10 -> 0 | I10: =H10 -> 0
A11: Представительские и подарки | E11: 30759 | G11: 12 | H11: =E11/G11 -> 2563.25 | I11: =H11 -> 2563.25
A12: Кап.вложения | I12: =D31 -> 23448.083
A13: Услуги Ук | E13: 720000 | G13: 12 | H13: =E13/G13 -> 60000 | I13: =H13 -> 60000
A14: Общие расходы Города | D14: =B19+B20 -> 13011 | F14: ='Общие расходы г. Альметьевск'!F4 -> 0.57570105 | I14: =D14*F14 -> 7490.4464
A15: Общие расходы ГЭ | D15: =B19+B20 -> 13011 | F15: ='Общие расходы ГЭ'!G16 -> 9.1731977 | I15: =D15*F15 -> 119352.47
A16: УСН | D16: =B19+B20 -> 13011 | F16: ='Общие расходы г. Тюмень'!F30 -> 0.74801393 | I16: =D16*F16 -> 9732.4093
I17: =SUM(I3:I16) -> 364358.82
A19: Абонентов домофония | B19: ='Исходные данные'!B40 -> 7606
A20: Абонентов ВН | B20: ='Исходные данные'!C40 -> 5405
A21: Подъездов | B21: ='Исходные данные'!D40 -> 229
A23: КАП.ВЛОЖЕНИЯ
A24: Наименование | B24: Общая сумма | C24: кол-во мес | D24: Итого
A25: ФОТ монтажи Касимов | B25: 270500 | C25: 12 | D25: =B25/C25 -> 22541.667
A26: ФОТ монтажи Богдан | B26: 6500 | C26: 12 | D26: =B26/C26 -> 541.66667
A27: расходники кап вложения | B27: 4377 | C27: 12 | D27: =B27/C27 -> 364.75
C28: 12 | D28: =B28/C28 -> 0
A31: ИТОГО | D31: =SUM(D25:D30) -> 23448.083

Sheet интернет юр лица
A1: УК | C1: 1 | D1: 2 | E1: 3 | F1: 4 | G1: 5 | H1: 6 | I1: 7 | J1: 8 | K1: 9 | L1: 10 | M1: 11 | N1: 12 | O1: сумма за год
A2: ЖСУ | B2: 50 лет окт 60 | C2: 1437.72 | D2: 1437.72 | E2: 1437.72 | F2: 1437.72 | G2: 1437.72 | H2: 1437.72 | I2: 1437.72 | J2: 1437.72 | K2: 1437.72 | L2: =-1066.7-1437.72 -> -2504.42 | O2: =SUM(B2:N2) -> 10435.06
A3: ЖСУ | B3: 50 лет окт 68 | C3: 1061.78 | D3: 1061.78 | E3: 1061.78 | F3: 1061.78 | G3: 1061.78 | H3: 1061.78 | I3: 1061.78 | J3: 1061.78 | K3: 1061.78 | L3: =-787.77-1061.78 -> -1849.55 | O3: =SUM(B3:N3) -> 7706.47
A4: Запад | B4: Белин 14 | C4: 1934.79 | D4: 1934.79 | E4: 1934.79 | F4: 1934.79 | G4: 1934.79 | H4: =-1934.79-1934.79 -> -3869.58 | O4: =SUM(B4:N4) -> 5804.37
A5: Запад | B5: Белин 28 | C5: 3289.14 | D5: 3289.14 | E5: 3289.14 | F5: 3289.14 | G5: 3289.14 | H5: =-3289.14-3289.14 -> -6578.28 | O5: =SUM(B5:N5) -> 9867.42
A6: Запад | B6: Бел 28а | C6: 849.42 | D6: 849.42 | E6: 849.42 | F6: 849.42 | G6: 849.42 | H6: 849.42 | I6: 849.42 | J6: =849.42+42.47 -> 891.89 | K6: 891.89 | L6: 891.89 | M6: 891.89 | N6: 891.89 | O6: =SUM(B6:N6) -> 10405.39
A7: Запад | B7: Моск 108 а | C7: 1437.72 | D7: 1437.72 | E7: 1437.72 | F7: 1437.72 | G7: 1437.72 | H7: 1437.72 | I7: 1437.72 | J7: 1437.72 | K7: =71.89+1509.61 -> 1581.5 | L7: 1509.61 | M7: 1509.61 | N7: 1509.61 | O7: =SUM(B7:N7) -> 17612.09
A8: Запад | B8: Моск 119 | C8: 3289.14 | D8: 3289.14 | E8: 3289.14 | F8: 3289.14 | G8: 3289.14 | H8: =-3289.14-3289.14 -> -6578.28 | O8: =SUM(B8:N8) -> 9867.42
A9: ЖСУ | B9: Перм 24 | C9: 4091.37 | D9: 4091.37 | E9: 4091.37 | F9: 4091.37 | G9: 4091.37 | H9: =-4091.37-4097.37 -> -8188.74 | O9: =SUM(B9:N9) -> 12268.11
A10: Запад | B10: Пролет 120 | C10: 1437.72 | D10: 1437.72 | E10: 1437.72 | F10: 1437.72 | G10: 1437.72 | H10: 1437.72 | I10: 1437.72 | J10: 1437.72 | K10: =71.79+1509.61 -> 1581.4 | L10: 1509.61 | M10: 1509.61 | N10: 1509.61 | O10: =SUM(B10:N10) -> 17611.99
A11: ЖСУ | B11: Респ 181 | C11: 1061.78 | D11: 1061.78 | E11: 1061.78 | F11: 1061.78 | G11: 1061.78 | H11: 1061.78 | I11: 1061.78 | J11: 1061.78 | K11: =53.08+114.68 -> 167.76 | L11: 1114.86 | M11: 1114.86 | N11: 1114.86 | O11: =SUM(B11:N11) -> 12006.58
A12: ЖСУ | B12: Рижс 63 | C12: 1132.56 | D12: 1132.56 | E12: 1132.56 | F12: 1132.56 | G12: 1132.56 | H12: 3132.56 | I12: =-913.35-1132.56 -> -2045.91 | O12: =SUM(B12:N12) -> 6749.45
A13: ЖСУ | B13: Рижс 80 | C13: 1934.79 | D13: 1934.79 | E13: 1934.79 | F13: 1934.79 | G13: 1934.79 | H13: 1934.79 | I13: 1934.79 | J13: 1934.79 | K13: =96.74+2031.53 -> 2128.27 | L13: 2031.53 | M13: 2031.53 | N13: 2031.53 | O13: =SUM(B13:N13) -> 23701.18
A14: ЖСУ | B14: Севаст 25 | C14: 1132.26 | D14: 1132.26 | E14: 1132.26 | F14: 1132.26 | G14: 1132.26 | H14: 1132.26 | I14: 1132.26 | J14: 1132.26 | K14: =56.63+1189.19 -> 1245.82 | L14: 1189.19 | M14: 1189.19 | N14: 1189.19 | O14: =SUM(B14:N14) -> 13871.47
A15: Запад | B15: Степ 1 а | C15: 2312.31 | D15: 2312.31 | E15: 2312.31 | F15: 2312.31 | G15: 2312.31 | H15: =-2312.31-2312.31 -> -4624.62 | O15: =SUM(B15:N15) -> 6936.93
A16: Запад | B16: Транс 108 | C16: =1132.56+3289.14 -> 4421.7 | D16: =1132.56+3289.14 -> 4421.7 | E16: =1132.56+3289.14 -> 4421.7 | F16: =1132.56+3289.14 -> 4421.7 | G16: =1132.56+3289.14 -> 4421.7 | H16: =1132.56+3289.14 -> 4421.7 | I16: =1132.56+3289.14 -> 4421.7 | J16: =1132.56+3289.14 -> 4421.7 | K16: =56.63+1189.19+164.46+3463.6 -> 4873.88 | L16: =1189.19+3453.6 -> 4642.79 | M16: =1189.19+3453.6 -> 4642.79 | N16: =1189.19+3453.6 -> 4642.79 | O16: =SUM(B16:N16) -> 54175.85
A17: Запад | B17: Ям 102а | C17: 849.42 | D17: 849.42 | E17: 849.42 | F17: 849.42 | G17: 849.42 | H17: 849.42 | I17: 849.42 | J17: 849.42 | K17: =42.47+891.89 -> 934.36 | L17: 891.89 | M17: 891.89 | N17: 891.89 | O17: =SUM(B17:N17) -> 10405.39
A18: Запад | B18: Ям 96 | C18: 3289.14 | D18: 3289.14 | E18: 3289.14 | F18: 3289.14 | G18: 3289.14 | H18: =-3289.14-3289.14 -> -6578.28 | O18: =SUM(B18:N18) -> 9867.42
P19: запад | Q19: =SUM(O4+O5+O6+O7+O8+O10+O15+O16+O17+O18) -> 152554.27
P20: ЖСУ | Q20: =SUM(O2+O3+O9+O11+O12+O13+O14) -> 86738.32

Sheet УК Альметьевск
A1: Альметьевск | B1: Всего на обсл. под. | C1: Кол-во под. по ук | D1: Кол-во абонентов | E1: Общая сумма | F1: кол-во мес | G1: Сумма за месяц | H1: р/аб | I1: Сумма расхода на УК
A2: ФОТ Васильев | B2: ='Исходные данные'!D43 -> 334 | C2: ='Исходные данные'!D41 -> 50 | E2: 278297 | F2: 12 | G2: =E2/F2 -> 23191.417 | I2: =G2/B2*C2 -> 3471.769
A3: ФОТ Касимов | B3: ='Исходные данные'!E43 -> 499 | C3: ='Исходные данные'!E41 -> 62 | E3: 695981 | F3: 12 | G3: =E3/F3 -> 57998.417 | I3: =G3/B3*C3 -> 7206.2161
A4: ФОТ | F4: 12 | G4: =E4/F4 -> 0 | I4: =G4 -> 0
A5: Интернет физ.лица | E5: =59635+3231 -> 62866 | F5: 12 | G5: =E5/F5 -> 5238.8333 | I5: =G5 -> 5238.8333
A6: Оборудование по УК | F6: 12 | G6: =E6/F6 -> 0 | I6: =G6 -> 0
A7: Расходники по УК | F7: 12 | G7: =E7/F7 -> 0 | I7: =G7 -> 0
A8: Транспортные | F8: 12 | G8: =E8/F8 -> 0 | I8: =G8 -> 0
A9: Представительские и подарки | E9: 9970 | F9: 12 | G9: =E9/F9 -> 830.83333 | I9: =G9 -> 830.83333
A10: Оборудование (Сервис) | E10: =50397+2299+4000 -> 56696 | F10: 12 | G10: =E10/F10 -> 4724.6667 | I10: =G10 -> 4724.6667
A11: Оборудование (Кап.вложения) | E11: 101207 | F11: 12 | G11: =E11/F11 -> 8433.9167 | I11: =G11 -> 8433.9167
A12: Оборудование (Модернизация) | F12: 12 | G12: =E12/F12 -> 0 | I12: =G12 -> 0
A13: Кап.вложение | I13: =D32 -> 0
A14: Услуги УК | E14: 182000 | F14: 12 | G14: =E14/F14 -> 15166.667 | I14: =G14 -> 15166.667
A15: Общие расходы по Городу | D15: =B20+B21 -> 1888 | H15: ='Общие расходы г. Альметьевск'!F4 -> 0.57570105 | I15: =D15*H15 -> 1086.9236
A16: Общие расходы ГЭ | D16: =B20+B21 -> 1888 | H16: ='Общие расходы ГЭ'!G16 -> 9.1731977 | I16: =D16*H16 -> 17318.997
A17: УСН | D17: =B20+B21 -> 1888 | H17: ='Общие расходы г. Тюмень'!F30 -> 0.74801393 | I17: =D17*H17 -> 1412.2503
I18: =SUM(I2:I17) -> 64891.073
A20: Абонентов домофония | B20: ='Исходные данные'!B41 -> 1219
A21: Абонентов ВН | B21: ='Исходные данные'!C41 -> 669
A22: Подъездов | B22: ='Исходные данные'!D41 -> 50
A24: КАП.ВЛОЖЕНИЯ
A25: Наименование | B25: Общая сумма | C25: кол-во мес | D25: Итого
A26: монтаж фот | C26: 12 | D26: =B26/C26 -> 0
A32: ИТОГО | D32: =SUM(D26:D31) -> 0

Sheet Новация
A1: Новация | B1: Всего на обсл. под. | C1: Кол-во под. по ук | D1: Кол-во абонентов | E1: Общая сумма | F1: кол-во мес | G1: р/аб | H1: Сумма за месяц | I1: Сумма расхода на УК
A2: ФОТ | B2: ='Исходные данные'!D43 -> 334 | C2: ='Исходные данные'!D42 -> 55 | E2: 278297 | F2: 12 | H2: =E2/F2 -> 23191.417 | I2: =H2/B2*C2 -> 3818.9459
A3: Оборудование (Сервис) | E3: =2854+382.5 -> 3236.5 | F3: 12 | H3: =E3/F3 -> 269.70833 | I3: =H3 -> 269.70833
A4: Общие расходы по Альм | D4: =B9+B10 -> 888 | G4: ='Общие расходы г. Альметьевск'!F4 -> 0.57570105 | I4: =D4*G4 -> 511.22253
A5: Общие расходы ГЭ | D5: =B9+B10 -> 888 | G5: ='Общие расходы ГЭ'!G16 -> 9.1731977 | I5: =D5*G5 -> 8145.7995
A6: усн | D6: =B9+B10 -> 888 | G6: ='Общие расходы г. Зеленодольск'!F12 -> 0.92421156 | I6: =D6*G6 -> 820.69986
I7: =SUM(I2:I6) -> 13566.376
A9: Абонентов домофония | B9: ='Исходные данные'!B42 -> 888
A10: Абонентов ВН | B10: ='Исходные данные'!C42 -> 0
A11: Подъездов | B11: ='Исходные данные'!D42 -> 55
A13: КАП.ВЛОЖЕНИЯ
A14: Наименование | B14: Общая сумма | C14: кол-во мес | D14: Итого

Sheet Жилкомплекс
A1: Жилкомплекс | B1: Всего на обсл. под. | C1: Кол-во под. по ук | D1: Кол-во абонентов | E1: Общая сумма | F1: кол-во мес | G1: р/аб | H1: Сумма за месяц | I1: Сумма расхода на УК
A2: ФОТ Калачев | B2: ='Исходные данные'!D53 -> 635 | C2: ='Исходные данные'!D46 -> 597 | E2: =8200+902051 -> 910251 | F2: 12 | H2: =E2/F2 -> 75854.25 | I2: =H2/B2*C2 -> 71314.941
A3: Интернет интердол+житель | E3: =8395+164548 -> 172943 | F3: 12 | H3: =E3/F3 -> 14411.917 | I3: =H3 -> 14411.917
A4: Оборудование по УК | F4: 12 | H4: =E4/F4 -> 0 | I4: =H4 -> 0
A5: Оборудование (Сервис) | E5: 268000 | F5: 12 | H5: =E5/F5 -> 22333.333 | I5: =H5 -> 22333.333
A6: Оборудование (Кап.вложения) | F6: 12 | H6: =E6/F6 -> 0 | I6: =H6 -> 0
A7: Оборудование (Модернизация) | E7: =700000+38000 -> 738000 | F7: 12 | H7: =E7/F7 -> 61500 | I7: =H7 -> 61500
A8: Услуги УК | E8: =539000+20000 -> 559000 | F8: 12 | H8: =E8/F8 -> 46583.333 | I8: =H8 -> 46583.333
A9: двери (фин помощь) | E9: 40000 | F9: 12 | H9: =E9/F9 -> 3333.3333
A10: Коммисия МаратРасход | F10: 12 | H10: =E10/F10 -> 0 | I10: =H10 -> 0
A11: Кап.вложение | H11: =D29 -> 25416.667 | I11: =H11 -> 25416.667
A12: Общие расходы ГЭ | D12: =B17+B18 -> 10796 | G12: ='Общие расходы ГЭ'!G16 -> 9.1731977 | I12: =D12*G12 -> 99033.842
A13: Общие расходы по Городу | D13: =B17+B18 -> 10796 | G13: ='Общие расходы г. Зеленодольск'!G4 -> 2.1346905 | I13: =D13*G13 -> 23046.118
A14: усн | D14: =B17+B18 -> 10796 | G14: ='Общие расходы г. Зеленодольск'!F12 -> 0.92421156 | I14: =D14*G14 -> 9977.788
I15: =SUM(I2:I14) -> 373617.94
A17: Абонентов домофония | B17: ='Исходные данные'!B46 -> 10796
A18: Абонентов ВН | B18: ='Исходные данные'!C46 -> 0
A19: Подъездов | B19: ='Исходные данные'!D46 -> 597 | I19: =I15/B19 -> 625.82569 | J19: 530
A21: МОДЕРНИЗАЦИЯ
A22: Наименование | B22: Общая сумма | C22: кол-во мес | D22: Итого
A23: Фот монтаж | B23: 276000 | C23: 12 | D23: =B23/C23 -> 23000
A24: подключение новых точек | B24: 29000 | C24: 12 | D24: =B24/C24 -> 2416.6667
A29: ИТОГО | D29: =SUM(D23:D28) -> 25416.667

Sheet Радужный_З
A1: радужный | B1: Всего на обсл. под. | C1: Кол-во под. по ук | D1: Кол-во абонентов | E1: Общая сумма | F1: кол-во мес | G1: р/аб | H1: Сумма за месяц | I1: Сумма расхода на УК
A2: ФОТ Калачев | B2: ='Исходные данные'!D53 -> 635 | C2: ='Исходные данные'!D48 -> 3 | E2: 902051 | F2: 12 | H2: =E2/F2 -> 75170.917 | I2: =H2/B2*C2 -> 355.13819
A3: Интернет физ.лица | E3: =21200+200 -> 21400 | F3: 12 | H3: =E3/F3 -> 1783.3333 | I3: =H3 -> 1783.3333
A4: Оборудование (Сервис) | E4: 0 | F4: 12 | H4: =E4/F4 -> 0 | I4: =H4 -> 0
A5: Оборудование по УК | F5: 12 | H5: =E5/F5 -> 0 | I5: =H5 -> 0
A6: Общие расходы ГЭ | D6: =B11+B12 -> 492 | G6: ='Общие расходы ГЭ'!G16 -> 9.1731977 | I6: =D6*G6 -> 4513.2132
A7: Общие расходы по Городу | D7: =B11+B12 -> 492 | G7: ='Общие расходы г. Зеленодольск'!G4 -> 2.1346905 | I7: =D7*G7 -> 1050.2677
A8: усн | D8: =B11+B12 -> 492 | G8: ='Общие расходы г. Зеленодольск'!F12 -> 0.92421156 | I8: =D8*G8 -> 454.71209
I9: =SUM(I2:I8) -> 8156.6646
A11: Абонентов домофония | B11: ='Исходные данные'!B48 -> 246
A12: Абонентов ВН | B12: ='Исходные данные'!C48 -> 246
A13: Подъездов | B13: ='Исходные данные'!D48 -> 3
A15: КАП.ВЛОЖЕНИЯ
A16: Наименование | B16: Общая сумма | C16: кол-во мес | D16: Итого

Sheet Салават Купере
A1: Салават Купере | B1: Всего на обсл. под. | C1: Кол-во под. по ук | D1: Кол-во абонентов | E1: Общая сумма | F1: кол-во мес | G1: р/аб | H1: Сумма за месяц | I1: Сумма расхода на УК
A2: ФОТ Калачев | B2: ='Исходные данные'!D53 -> 635 | C2: ='Исходные данные'!D48 -> 3 | E2: 902051 | F2: 12 | H2: =E2/F2 -> 75170.917 | I2: =H2/B2*C2 -> 355.13819
A3: Общие расходы ГЭ | D3: =B8+B9 -> 114 | G3: ='Общие расходы ГЭ'!G16 -> 9.1731977 | I3: =D3*G3 -> 1045.7445
A4: Общие расходы по Городу | D4: =B8+B9 -> 114 | G4: ='Общие расходы г. Зеленодольск'!G4 -> 2.1346905 | I4: =D4*G4 -> 243.35472
A5: усн | D5: =B8+B9 -> 114 | G5: ='Общие расходы г. Зеленодольск'!F12 -> 0.92421156 | I5: =D5*G5 -> 105.36012
I6: =SUM(I2:I5) -> 1749.5976
A8: Абонентов домофония | B8: ='Исходные данные'!B47 -> 114
A9: Абонентов ВН | B9: ='Исходные данные'!C47 -> 0
A10: Подъездов | B10: ='Исходные данные'!D47 -> 3
A12: КАП.ВЛОЖЕНИЯ
A13: Наименование | B13: Общая сумма | C13: кол-во мес | D13: Итого

Sheet ТСЖ №6
A1: ТСЖ6 | B1: Всего на обсл. под. | C1: Кол-во под. по ук | D1: Кол-во абонентов | E1: Общая сумма | F1: кол-во мес | G1: р/аб | H1: Сумма за месяц | I1: Сумма расхода на УК
A2: ФОТ Калачев | B2: ='Исходные данные'!D53 -> 635 | C2: ='Исходные данные'!D49 -> 4 | E2: 902051 | F2: 12 | H2: =E2/F2 -> 75170.917 | I2: =H2/B2*C2 -> 473.51759
A3: Интернет | E3: 6024 | F3: 12 | H3: =E3/F3 -> 502 | I3: =H3 -> 502
A4: Кап.вложение | I4: =D23 -> 0
A5: Оборудование (Сервис) | E5: 26 | F5: 12 | H5: =E5/F5 -> 2.1666667 | I5: =H5 -> 2.1666667
A6: Общие расходы ГЭ | D6: =B11+B12 -> 288 | G6: ='Общие расходы ГЭ'!G16 -> 9.1731977 | I6: =D6*G6 -> 2641.8809
A7: Общие расходы по Городу | D7: =B11+B12 -> 288 | G7: ='Общие расходы г. Зеленодольск'!G4 -> 2.1346905 | I7: =D7*G7 -> 614.79086
A8: усн | D8: =B11+B12 -> 288 | G8: ='Общие расходы г. Зеленодольск'!F12 -> 0.92421156 | I8: =D8*G8 -> 266.17293
I9: =SUM(I2:I8) -> 4500.529
A11: Абонентов домофония | B11: ='Исходные данные'!B49 -> 288
A12: Абонентов ВН | B12: ='Исходные данные'!C49 -> 0
A13: Подъездов | B13: ='Исходные данные'!D49 -> 4
A15: КАП.ВЛОЖЕНИЯ
A16: Наименование | B16: Общая сумма | C16: кол-во мес | D16: Итого
D23: =SUM(D17:D22) -> 0

Sheet Прямые
A1: прямые | B1: Всего на обсл. под. | C1: Кол-во под. по ук | D1: Кол-во абонентов | E1: Общая сумма | F1: кол-во мес | G1: р/аб | H1: Сумма за месяц | I1: Сумма расхода на УК
A2: ФОТ Калачев | B2: ='Исходные данные'!D53 -> 635 | C2: ='Исходные данные'!D52 -> 9 | E2: 902051 | F2: 12 | H2: =E2/F2 -> 75170.917 | I2: =H2/B2*C2 -> 1065.4146
A3: Кап.влажение | E3: 0 | I3: =D22 -> 0
A4: Оборудование (Модернизация) | E4: 0 | F4: 12 | H4: =E4/F4 -> 0 | I4: =H4 -> 0
A5: Общие расходы ГЭ | D5: =B10+B11 -> 283 | G5: ='Общие расходы ГЭ'!G16 -> 9.1731977 | I5: =D5*G5 -> 2596.0149
A6: Общие расходы по Городу | D6: =B10+B11 -> 283 | G6: ='Общие расходы г. Зеленодольск'!G4 -> 2.1346905 | I6: =D6*G6 -> 604.11741
A7: усн | D7: =B10+B11 -> 283 | G7: ='Общие расходы г. Зеленодольск'!F12 -> 0.92421156 | I7: =D7*G7 -> 261.55187
I8: =SUM(I2:I7) -> 4527.0988
A10: Абонентов домофония | B10: ='Исходные данные'!B52 -> 283
A11: Абонентов ВН | B11: ='Исходные данные'!C52 -> 0
A12: Подъездов | B12: ='Исходные данные'!D52 -> 9
A14: КАП.ВЛОЖЕНИЯ
A15: Наименование | B15: Общая сумма | C15: кол-во мес | D15: Итого
A16: фот монтаж | C16: 12 | D16: =B16/C16 -> 0
D22: =SUM(D16:D21) -> 0

Sheet ЖК Моск рай-на
A1: моск района | B1: всего на обслуж | C1: Кол-во абонентов | D1: Общая сумма | E1: кол-во мес | F1: р/аб | G1: Сумма за месяц | H1: Сумма расхода на УК
A2: ФОТ Ильдус ВН | B2: ='Исходные данные'!D56 -> 12 | C2: =B2 -> 12 | D2: 112500 | E2: 12 | G2: =D2/E2 -> 9375 | H2: =G2/B2*C2 -> 9375
A3: ФОТ доп Ильдус | D3: 2000 | E3: 12 | G3: =D3/E3 -> 166.66667 | H3: =G3 -> 166.66667
A4: Интернет физ.лица | D4: =90246+4015 -> 94261 | E4: 12 | G4: =D4/E4 -> 7855.0833 | H4: =G4 -> 7855.0833
A5: Оборудование (Кап.вложения) | D5: 139522 | E5: 12 | G5: =D5/E5 -> 11626.833 | H5: =G5 -> 11626.833
A6: Оборудование (Сервис) | D6: =11400+2250 -> 13650 | E6: 12 | G6: =D6/E6 -> 1137.5 | H6: =G6 -> 1137.5
A7: Представительские и подарки | D7: =2966.44+840 -> 3806.44 | E7: 12 | G7: =D7/E7 -> 317.20333 | H7: =G7 -> 317.20333
A8: Расходники по УК | D8: 6530 | E8: 12 | G8: =D8/E8 -> 544.16667 | H8: =G8 -> 544.16667
A9: канц товары | D9: 624 | E9: 12 | G9: =D9/E9 -> 52 | H9: =G9 -> 52
A10: Кап.вложения | H10: =D29 -> 5400
A11: Общие расходы Города | C11: =B16+B17 -> 1674 | F11: ='Общие расходы г. Казань'!F4 -> 0 | H11: =C11*F11 -> 0
A12: Общие расходы ГЭ | C12: =B16+B17 -> 1674 | F12: ='Общие расходы ГЭ'!G16 -> 9.1731977 | H12: =C12*F12 -> 15355.933
A13: УСН | C13: =B16+B17 -> 1674 | F13: ='Общие расходы г. Зеленодольск'!F12 -> 0.92421156 | H13: =C13*F13 -> 1547.1301
H14: =SUM(H2:H13) -> 53377.516
A16: Абонентов домофония | B16: ='Исходные данные'!B56 -> 192
A17: Абонентов ВН | B17: ='Исходные данные'!C56 -> 1482
A18: Подъездов | B18: ='Исходные данные'!D56 -> 12
A20: КАП.ВЛОЖЕНИЯ
A21: Наименование | B21: Общая сумма | C21: кол-во мес | D21: Итого
A22: фот монтаж | B22: =5000+34500 -> 39500 | C22: 12 | D22: =B22/C22 -> 3291.6667
A23: голосование | B23: 25300 | C23: 12 | D23: =B23/C23 -> 2108.3333
A24: подключение новой точки | C24: 12 | D24: =B24/C24 -> 0
D29: =SUM(D22:D28) -> 5400

Sheet Радужный (Казань)
A1: РАДУЖНЫЙ | B1: Всего на обсл. под. | C1: Кол-во под. по ук | D1: Кол-во абонентов | E1: Общая сумма | F1: кол-во мес | G1: р/аб | H1: Сумма за месяц | I1: Сумма расхода на УК
A2: ФОТ Ильдус | B2: ='Исходные данные'!D61 -> 96 | C2: ='Исходные данные'!D58 -> 75 | E2: 130524 | F2: 12 | H2: =E2/F2 -> 10877 | I2: =H2/B2*C2 -> 8497.6562
A3: Интернет физ.лица | E3: =6110+30 -> 6140 | F3: 12 | H3: =E3/F3 -> 511.66667 | I3: =H3 -> 511.66667
A4: сервис | F4: 12 | H4: =E4/F4 -> 0
A5: Кап.вложения | E5: 26676 | F5: 12 | H5: =E5/F5 -> 2223 | I5: =D24 -> 0
A6: Оборудование по УК | F6: 12 | H6: =E6/F6 -> 0 | I6: =H6 -> 0
A7: Общие расходы Города | D7: =B12+B13 -> 1271 | G7: ='Общие расходы г. Казань'!F4 -> 0 | I7: =D7*G7 -> 0
A8: Общие расходы ГЭ | D8: =B12+B13 -> 1271 | G8: ='Общие расходы ГЭ'!G16 -> 9.1731977 | I8: =D8*G8 -> 11659.134
A9: УСН | D9: =B12+B13 -> 1271 | G9: ='Общие расходы г. Зеленодольск'!F12 -> 0.92421156 | I9: =D9*G9 -> 1174.6729
I10: =SUM(I2:I9) -> 21843.13
A12: Абонентов домофония | B12: ='Исходные данные'!B58 -> 1271
A13: Абонентов ВН | B13: ='Исходные данные'!C58 -> 0
A14: Подъездов | B14: ='Исходные данные'!D58 -> 75
A16: КАП.ВЛОЖЕНИЯ
A17: Наименование | B17: Общая сумма | C17: кол-во мес | D17: Итого
C18: 12 | D18: =B18/C18 -> 0
A24: ИТОГО | D24: =SUM(D18:D23) -> 0

Sheet Фукса 12
A1: фукса 12 | B1: Всего на обсл. под. | C1: Кол-во под. по ук | D1: Кол-во абонентов | E1: Общая сумма | F1: кол-во мес | G1: р/аб | H1: Сумма за месяц | I1: Сумма расхода на УК
A2: ФОТ Ильдус | B2: ='Исходные данные'!D61 -> 96 | C2: ='Исходные данные'!D57 -> 5 | E2: 130524 | F2: 12 | H2: =E2/F2 -> 10877 | I2: =H2/B2*C2 -> 566.51042
A3: Оборудование | E3: 0 | F3: 12 | H3: =E3/F3 -> 0 | I3: =H3 -> 0
A4: Общие расходы Города | D4: =B9+B10 -> 40 | G4: ='Общие расходы г. Казань'!F4 -> 0 | I4: =D4*G4 -> 0
A5: Общие расходы ГЭ | D5: =B9+B10 -> 40 | G5: ='Общие расходы ГЭ'!G16 -> 9.1731977 | I5: =D5*G5 -> 366.92791
A6: усн | D6: =B9+B10 -> 40
I7: =SUM(I2:I6) -> 933.43832
A9: Абонентов домофония | B9: ='Исходные данные'!B57 -> 40
A10: Абонентов ВН | B10: ='Исходные данные'!C57 -> 0
A11: Подъездов | B11: ='Исходные данные'!D57 -> 5
A13: КАП.ВЛОЖЕНИЯ
A14: Наименование | B14: Общая сумма | C14: кол-во мес | D14: Итого

Sheet ТСЖ Соврменник
A2: ЖСУ | B2: Всего на обсл. под. | C2: Кол-во под. по ук | D2: Кол-во абонентов | E2: Общая сумма | F2: кол-во мес | G2: Сумма за месяц | H2: р/аб | I2: Сумма расхода на УК
A3: ФОТ Ильдус | B3: ='Исходные данные'!D61 -> 96 | C3: ='Исходные данные'!D59 -> 4 | E3: 130524 | F3: 12 | G3: =E3/F3 -> 10877 | I3: =G3/B3*C3 -> 453.20833
A4: Интернет ЭРТХ | F4: 12 | G4: =E4/F4 -> 0 | I4: =G4 -> 0
A5: Интернет йота | F5: 12 | G5: =E5/F5 -> 0 | I5: =G5 -> 0
A6: Оборудование (Сервис) | E6: 1075 | F6: 12 | G6: =E6/F6 -> 89.583333 | I6: =G6 -> 89.583333
A7: Оборудование (Кап.вложения) | E7: 0 | F7: 12 | G7: =E7/F7 -> 0 | I7: =G7 -> 0
A8: Оборудование (Модернизация) | E8: 0 | F8: 12 | G8: =E8/F8 -> 0 | I8: =G8 -> 0
A9: Расходники по УК | F9: 12 | G9: =E9/F9 -> 0 | I9: =G9 -> 0
A10: кап.вложения | I10: =D23 -> 0
A11: Транспортные по УК | F11: 12 | G11: =E11/F11 -> 0 | I11: =G11 -> 0
A12: Общие расходы ГЭ | D12: =B17+B18 -> 360 | H12: ='Общие расходы ГЭ'!G16 -> 9.1731977 | I12: =D12*H12 -> 3302.3512
A13: Общие расходы по городу | D13: =B17+B18 -> 360 | H13: ='Общие расходы г. Казань'!F4 -> 0 | I13: =D13*H13 -> 0
A14: УСН | D14: =B17+B18 -> 360 | H14: ='Общие расходы г. Зеленодольск'!F12 -> 0.92421156 | I14: =D14*H14 -> 332.71616
I15: =SUM(I3:I14) -> 4177.859
A17: Абонентов домофония | B17: ='Исходные данные'!B59 -> 360
A18: Абонентов ВН | B18: ='Исходные данные'!C64 -> 0
A19: Подъездов | B19: ='Исходные данные'!D59 -> 4
A21: КАП.ВЛОЖЕНИЯ
A22: Наименование | B22: Общая сумма | C22: кол-во мес | D22: Итого
A23: фот монтадж | C23: 12 | D23: =B23/C23 -> 0

Sheet ЭРТХ_К
A1: ЭРТХ | B1: всего на обслуж | C1: подъезды ЭРТХ | D1: Общая сумма | E1: кол-во мес | F1: р/аб | G1: сумма из фота на ЭРТХ
A2: ФОТ | B2: 18724 | C2: ='Исходные данные'!B60 -> 18724 | D2: =2145371+42000+30000 -> 2217371 | E2: 12 | G2: =D2/E2 -> 184780.92
A3: Участив в тендере | D3: =10000+5200 -> 15200 | E3: 12 | G3: =D3/E3 -> 1266.6667
A4: Общие расходы ГЭ | F4: ='Общие расходы ГЭ'!G16 -> 9.1731977 | G4: =B4*F4 -> 0
G5: =SUM(G2:G4) -> 186047.58

Sheet Тринити
A1: Тринити | B1: Всего на обсл. под. | C1: Кол-во под. по ук | D1: Кол-во абонентов | E1: Общая сумма | F1: кол-во мес | G1: р/аб | H1: Сумма за месяц | I1: Сумма расхода на УК
A2: ФОТ Калачев | B2: ='Исходные данные'!D53 -> 635 | C2: ='Исходные данные'!D50 -> 15 | E2: 66000 | F2: 12 | H2: =E2/F2 -> 5500 | I2: =H2/B2*C2 -> 129.92126
A3: ФОТ Калачев вн
A4: Интернет йота | E4: =78906+4065 -> 82971 | F4: 12 | H4: =E4/F4 -> 6914.25 | I4: =E4/F4 -> 6914.25
A5: Оборудование (Сервис) | E5: =61519+1140+5569 -> 68228 | F5: 12 | H5: =E5/F5 -> 5685.6667 | I5: =E5/F5 -> 5685.6667
A6: Общие расходы ГЭ | D6: =B12+B13 -> 170 | G6: ='Общие расходы ГЭ'!G16 -> 9.1731977 | I6: =D6*G6 -> 1559.4436
A7: Общие расходы по Городу | D7: =B12+B13 -> 170 | G7: ='Общие расходы г. Инно'!F4 -> 1.689071 | I7: =D7*G7 -> 287.14208
A8: усн | D8: =B12+B13 -> 170 | G8: ='Общие расходы г. Зеленодольск'!F12 -> 0.92421156 | I8: =D8*G8 -> 157.11596
I9: =SUM(I2:I8) -> 14733.54
A12: Абонентов домофония | B12: ='Исходные данные'!B69 -> 78
A13: Абонентов ВН | B13: ='Исходные данные'!C69 -> 92
A14: Подъездов | B14: ='Исходные данные'!D69 -> 15
F15: 80 камер тринити
A16: КАП.ВЛОЖЕНИЯ
A17: Наименование | B17: Общая сумма | C17: кол-во мес | D17: Итого

Sheet ЗИОН
A1: ЗИОН | B1: Всего на обсл. под. | C1: Кол-во под. по ук | D1: Кол-во абонентов | E1: Общая сумма | F1: кол-во мес | G1: р/аб | H1: Сумма за месяц | I1: Сумма расхода на УК
A2: ФОТ Калачев | B2: 104 | C2: 23 | E2: 66000 | F2: 12 | H2: =E2/F2 -> 5500 | I2: =H2/B2*C2 -> 1216.3462
A3: Интернет йота | E3: =74755+650 -> 75405 | F3: 12 | H3: =E3/F3 -> 6283.75 | I3: =H3 -> 6283.75
A4: Доп. работы | F4: 12 | H4: =E4/F4 -> 0 | I4: =H4 -> 0
A5: Оборудование (Сервис) | E5: =31776+5500+10000 -> 47276 | F5: 12 | H5: =E5/F5 -> 3939.6667 | I5: =H5 -> 3939.6667
A6: Оборудование по ук | F6: 12 | H6: =E6/F6 -> 0 | I6: =H6 -> 0
A7: Общие расходы ГЭ | D7: =B14 -> 440 | G7: ='Общие расходы ГЭ'!G16 -> 9.1731977 | I7: =D7*G7 -> 4036.207
A8: Общие расходы по Городу | D8: =B14 -> 440 | G8: ='Общие расходы г. Инно'!F4 -> 1.689071 | I8: =D8*G8 -> 743.19126
A9: усн | D9: =B14 -> 440 | G9: ='Общие расходы г. Зеленодольск'!F12 -> 0.92421156 | I9: =D9*G9 -> 406.65308
I10: =SUM(I2:I9) -> 16625.814
A13: Абонентов домофонии | B13: ='Исходные данные'!B70 -> 0
A14: Абонентов ВН | B14: ='Исходные данные'!C70 -> 440
A15: Подъездов | B15: 0 | G15: 23 камеры зион застройщик
A17: КАП.ВЛОЖЕНИЯ
A18: Наименование | B18: Общая сумма | C18: кол-во мес | D18: Итого

Sheet Жилищный фонд
A1: Жилищный фонд | B1: Всего на обсл. под. | C1: Кол-во под. по ук | D1: Кол-во абонентов | E1: Общая сумма | F1: кол-во мес | G1: р/аб | H1: Сумма за месяц | I1: Сумма расхода на УК
A2: ФОТ Калачев | B2: 0 | C2: 0 | E2: 25800 | F2: 12 | H2: =E2/F2 -> 2150 | I2: =H2 -> 2150
A3: Оборудование по УК | F3: 12 | H3: =E3/F3 -> 0 | I3: =H3 -> 0
A4: Оборудование (Сервис) | E4: 0
A5: Общие расходы ГЭ | D5: =B10 -> 1115 | G5: ='Общие расходы ГЭ'!G16 -> 9.1731977 | I5: =D5*G5 -> 10228.115
A6: Общие расходы по Городу | D6: =B10 -> 1115 | G6: ='Общие расходы г. Инно'!F4 -> 1.689071 | I6: =D6*G6 -> 1883.3142
A7: усн | D7: =B10 -> 1115 | I7: =D7*G7 -> 0
I8: =SUM(I2:I7) -> 14261.43
A10: Абонентов биометрия | B10: ='Исходные данные'!B65 -> 1115
A11: Абонентов ВН | B11: ='Исходные данные'!C65 -> 0
A12: Подъездов | B12: ='Исходные данные'!D66 -> 46
A14: КАП.ВЛОЖЕНИЯ
A15: Наименование | B15: Общая сумма | C15: кол-во мес | D15: Итого

Sheet СК Иннокомфорт
A1: СК Иннокомфорт | B1: Всего на обсл. под. | C1: Кол-во под. по ук | D1: Кол-во абонентов | E1: Общая сумма | F1: кол-во мес | G1: р/аб | H1: Сумма за месяц | I1: Сумма расхода на УК
A2: ФОТ Калачев | B2: ='Исходные данные'!D53 -> 635 | C2: ='Исходные данные'!D51 -> 4 | E2: 902051 | F2: 12 | H2: =E2/F2 -> 75170.917 | I2: =H2/B2*C2 -> 473.51759
A3: Интернет йота | E3: 14925 | F3: 12 | H3: =E3/F3 -> 1243.75 | I3: =H3 -> 1243.75
A4: Оборудование | E4: 26666 | F4: 12 | H4: =E4/F4 -> 2222.1667 | I4: =H4 -> 2222.1667
A5: Общие расходы ГЭ | D5: =B10 -> 105 | G5: ='Общие расходы ГЭ'!G16 -> 9.1731977 | I5: =D5*G5 -> 963.18575
A6: Общие расходы по Городу | D6: =B10 -> 105 | G6: ='Общие расходы г. Инно'!F4 -> 1.689071 | I6: =D6*G6 -> 177.35246
A7: усн | D7: =B10 -> 105 | G7: ='Общие расходы г. Зеленодольск'!F12 -> 0.92421156 | I7: =D7*G7 -> 97.042213
I8: =SUM(I2:I7) -> 5177.0147
A10: Абонентов домофонии | B10: ='Исходные данные'!B64 -> 105
A11: Абонентов ВН | B11: ='Исходные данные'!C64 -> 0
A12: Подъездов | B12: ='Исходные данные'!D64 -> 4
A14: КАП.ВЛОЖЕНИЯ
A15: Наименование | B15: Общая сумма | C15: кол-во мес | D15: Итого
